Workbook

Sheet Config
A1: Additional Configuration
A2: Please select your language: | B2: EN-US

Sheet Exec Summary
B2: These graphs are based off the priorities your organization has assigned to each product in the "SCIMP Plan" tab below (SCIMP = Security, Compliance, Identity, Management and Privacy), and represent total value for the area in the chart title. Detail of your overall maturity can be found in the "Maturity Matrix" tab below.
B4: Realized and Desired Value from current and prospective licensing
C6: Green represents value your are getting from the respective area of techology. It is the combination of what is currently deployed or being deployed (Work in Progress)
C7: Amber represents the total technologies and configurations that your organization can see value in. It is the combination of all technologies that have been given an active deployment priority
C8: Grey represents technologies and configurations that either have not been assessed or your organization sees no value today
B10: Overall view of all technologies (Please note: These include all products and features and exclude configurations, considerations, suggestions and processes)
C11: Overvalue of all Technologies | J11: E3 Current Value | R11: E5 Current Value | X11: Azure Current Value
C12: Realising Value | D12: {=SUM(COUNTIFS('SCIMP Plan'!F3:F241,{"D","W"},'SCIMP Plan'!C3:C241,"Product") + COUNTIFS('SCIMP Plan'!F3:F241,{"D","W"},'SCIMP Plan'!C3:C241,"Feature"))} -> 0 | J12: Realising value from E3 | K12: {=SUM(COUNTIFS('SCIMP Plan'!F3:F241,{"D","W"},'SCIMP Plan'!B3:B241,"*M365 E3*",'SCIMP Plan'!C3:C241,"Feature") + COUNTIFS('SCIMP Plan'!F3:F241,{"D","W"},'SCIMP Plan'!B3:B241,"*M365 E3*",'SCIMP Plan'!C3:C241,"Product"))} -> 0 | R12: Realised Value from E5 | S12: {=SUM(COUNTIFS('SCIMP Plan'!F3:F241,{"D","W"},'SCIMP Plan'!B3:B241,"*M365 Defender*",'SCIMP Plan'!C3:C241,"Feature") + COUNTIFS('SCIMP Plan'!F3:F241,{"D","W"},'SCIMP Plan'!B3:B241,"*M365 Purview*",'SCIMP Plan'!C3:C241,"Product"))} -> 0 | X12: Realising value from Azure Security | Y12: {=SUM(COUNTIFS('SCIMP Plan'!F3:F241,{"D","W"},'SCIMP Plan'!B3:B241,"*Azure*",'SCIMP Plan'!C3:C241,"Feature") + COUNTIFS('SCIMP Plan'!F3:F241,{"D","W"},'SCIMP Plan'!B3:B241,"*Azure*",'SCIMP Plan'!C3:C241,"Product"))} -> 0
C13: Desired Technologies | D13: {=SUM(COUNTIFS('SCIMP Plan'!F3:F241,{"1","2","3"},'SCIMP Plan'!C3:C241,"Product") + COUNTIFS('SCIMP Plan'!F3:F241,{"1","2","3"},'SCIMP Plan'!C3:C241,"Feature"))} -> 0 | J13: Desired E3 Technologies | K13: {=SUM(COUNTIFS('SCIMP Plan'!F3:F241,{"1","2","3"},'SCIMP Plan'!B3:B241,"*M365 E3*",'SCIMP Plan'!C3:C241,"Feature") + COUNTIFS('SCIMP Plan'!F3:F241,{"1","2","3"},'SCIMP Plan'!B3:B241,"*M365 E3*",'SCIMP Plan'!C3:C241,"Product"))} -> 0 | R13: Desired E5 Tech | S13: {=SUM(COUNTIFS('SCIMP Plan'!F3:F241,{"1","2","3"},'SCIMP Plan'!B3:B241,"*M365 Defender*",'SCIMP Plan'!C3:C241,"Feature") + COUNTIFS('SCIMP Plan'!F3:F241,{"1","2","3"},'SCIMP Plan'!B3:B241,"*M365 Purview*",'SCIMP Plan'!C3:C241,"Product")+ COUNTIFS('SCIMP Plan'!F3:F241,{"1","2","3"},'SCIMP Plan'!B3:B241,"*M365 E5*",'SCIMP Plan'!C3:C241,"Product"))} -> 0 | X13: Desired Azure Security Technologies | Y13: {=SUM(COUNTIFS('SCIMP Plan'!F3:F241,{"1","2","3"},'SCIMP Plan'!B3:B241,"*Azure*",'SCIMP Plan'!C3:C241,"Feature") + COUNTIFS('SCIMP Plan'!F3:F241,{"1","2","3"},'SCIMP Plan'!B3:B241,"*Azure*",'SCIMP Plan'!C3:C241,"Product"))} -> 0
C14: No Intent or not yet assessed | D14: {=SUM(COUNTIFS('SCIMP Plan'!F3:F241,{"-","4"},'SCIMP Plan'!C3:C241,"Product") + COUNTIFS('SCIMP Plan'!F3:F241,{"-","4"},'SCIMP Plan'!C3:C241,"Feature"))} -> 151 | J14: Not assessed or superceed by E5 | K14: {=SUM(COUNTIFS('SCIMP Plan'!F3:F241,{"-","4"},'SCIMP Plan'!B3:B241,"*M365 E3*",'SCIMP Plan'!C3:C241,"Feature") + COUNTIFS('SCIMP Plan'!F3:F241,{"-","4"},'SCIMP Plan'!B3:B241,"*M365 E3*",'SCIMP Plan'!C3:C241,"Product"))} -> 58 | R14: Not yet assessed or no intent to deploy | S14: {=SUM(COUNTIFS('SCIMP Plan'!F3:F241,{"-","4"},'SCIMP Plan'!B3:B241,"*M365 Defender*",'SCIMP Plan'!C3:C241,"Feature") + COUNTIFS('SCIMP Plan'!F3:F241,{"-","4"},'SCIMP Plan'!B3:B241,"*M365 Purview*",'SCIMP Plan'!C3:C241,"Product"))} -> 37 | X14: No intent or not yet assessed | Y14: {=SUM(COUNTIFS('SCIMP Plan'!F3:F241,{"-","4"},'SCIMP Plan'!B3:B241,"*Azure*",'SCIMP Plan'!C3:C241,"Feature") + COUNTIFS('SCIMP Plan'!F3:F241,{"-","4"},'SCIMP Plan'!B3:B241,"*Azure*",'SCIMP Plan'!C3:C241,"Product"))} -> 31
K15: E3 | S15: E5 | Y15: Azure
B27: View of Microsoft 365 E5 Technologies (This section shows the current and desired value from all M365 E5 products features)
C31: M365 E5 Core Products | J31: M365 E5 Deeper Product Features | P31: Core Products: These are the individual full products within the respective license
C32: Realised value | D32: {=SUM(COUNTIFS('SCIMP Plan'!F3:F241,{"D","W"},'SCIMP Plan'!B3:B241,{"*M365 Defender*"},'SCIMP Plan'!C3:C241,'Data Validations'!D2) + COUNTIFS('SCIMP Plan'!F3:F241,{"D","W"},'SCIMP Plan'!B3:B241,{"*M365 Purview*"},'SCIMP Plan'!C3:C241,'Data Validations'!D2))} -> 0 | J32: Realised value | K32: {=SUM(COUNTIFS('SCIMP Plan'!F3:F241,{"D","W"},'SCIMP Plan'!B3:B241,{"*M365 Defender*"},'SCIMP Plan'!C3:C241,'Data Validations'!D3) + COUNTIFS('SCIMP Plan'!F3:F241,{"D","W"},'SCIMP Plan'!B3:B241,{"*M365 Purview*"},'SCIMP Plan'!C3:C241,'Data Validations'!D3))} -> 0
C33: Desired Features | D33: {=SUM(COUNTIFS('SCIMP Plan'!F3:F241,{"1","2","3"},'SCIMP Plan'!B3:B241,{"*M365 Defender*"},'SCIMP Plan'!C3:C241,'Data Validations'!D2) + COUNTIFS('SCIMP Plan'!F3:F241,{"1","2","3"},'SCIMP Plan'!B3:B241,{"*M365 Purview"},'SCIMP Plan'!C3:C241,'Data Validations'!D2))} -> 0 | J33: Desired Features | K33: {=SUM(COUNTIFS('SCIMP Plan'!F3:F241,{"1","2","3"},'SCIMP Plan'!B3:B241,{"*M365 Defender*"},'SCIMP Plan'!C3:C241,'Data Validations'!D3) + COUNTIFS('SCIMP Plan'!F3:F241,{"1","2","3"},'SCIMP Plan'!B3:B241,{"*M365 Purview*"},'SCIMP Plan'!C3:C241,'Data Validations'!D3))} -> 0 | P33: Deeper Product Features: These are call out features within a product
C34: Not assessed or no value | D34: {=SUM(COUNTIFS('SCIMP Plan'!F3:F241,{"-","4"},'SCIMP Plan'!B3:B241,{"*M365 Defender*"},'SCIMP Plan'!C3:C241,'Data Validations'!D2) + COUNTIFS('SCIMP Plan'!F3:F241,{"-","4"},'SCIMP Plan'!B3:B241,{"*M365 Purview*"},'SCIMP Plan'!C3:C241,'Data Validations'!D2))} -> 39 | J34: Not assessed or no value | K34: {=SUM(COUNTIFS('SCIMP Plan'!F3:F241,{"-","4"},'SCIMP Plan'!B3:B241,{"*M365 Defender*"},'SCIMP Plan'!C3:C241,'Data Validations'!D3) + COUNTIFS('SCIMP Plan'!F3:F241,{"-","4"},'SCIMP Plan'!B3:B241,{"*M365 Purview*"},'SCIMP Plan'!C3:C241,'Data Validations'!D3))} -> 32
P35: Optional Configuration: These are recommended configurations, considerations, suggestions and process that align to best practices
B44: Break down E5 Security and Compliance SKUs (This sections breaks down the M365 E5 features into E5 Security and E5 Compliance)
C45: M365 E5 Security Core Products | K45: M365 E5 Security Deeper Product Features
C46: Realised value | D46: {=SUM(COUNTIFS('SCIMP Plan'!F3:F241,{"D","W"},'SCIMP Plan'!B3:B241,"*Defender*",'SCIMP Plan'!C3:C241,'Data Validations'!D2))} -> 0 | K46: Realised value | L46: {=SUM(COUNTIFS('SCIMP Plan'!F3:F241,{"D","W"},'SCIMP Plan'!B3:B241,"*Defender*",'SCIMP Plan'!C3:C241,'Data Validations'!D3))} -> 0 | R46: M365 E5 Compliance Core Products
C47: Desired Features | D47: {=SUM(COUNTIFS('SCIMP Plan'!F3:F241,{"1","2","3"},'SCIMP Plan'!B3:B241,"*Defender*",'SCIMP Plan'!C3:C241,'Data Validations'!D2))} -> 0 | K47: Desired Features | L47: {=SUM(COUNTIFS('SCIMP Plan'!F3:F241,{"1","2","3"},'SCIMP Plan'!B3:B241,"*Defender*",'SCIMP Plan'!C3:C241,'Data Validations'!D3))} -> 0 | R47: Realised value | S47: {=SUM(COUNTIFS('SCIMP Plan'!F3:F241,{"D","W"},'SCIMP Plan'!B3:B241,"*Purview*",'SCIMP Plan'!C3:C241,"Product"))} -> 0 | X47: M365 E5 Compliance Deeper Product Features
C48: Not assessed or no value | D48: {=SUM(COUNTIFS('SCIMP Plan'!F3:F241,{"-","4"},'SCIMP Plan'!B3:B241,"*Defender*",'SCIMP Plan'!C3:C241,'Data Validations'!D2))} -> 25 | K48: Not assessed or no value | L48: {=SUM(COUNTIFS('SCIMP Plan'!F3:F241,{"-","4"},'SCIMP Plan'!B3:B241,"*Defender*",'SCIMP Plan'!C3:C241,'Data Validations'!D3))} -> 21 | R48: Desired Features | S48: {=SUM(COUNTIFS('SCIMP Plan'!F3:F241,{"1","2","3"},'SCIMP Plan'!B3:B241,"*Purview*",'SCIMP Plan'!C3:C241,"Product"))} -> 0 | X48: Realised value | Y48: {=SUM(COUNTIFS('SCIMP Plan'!F3:F241,{"D","W"},'SCIMP Plan'!B3:B241,"*Purview*",'SCIMP Plan'!C3:C241,"feature"))} -> 0
R49: Not assessed or no value | S49: {=SUM(COUNTIFS('SCIMP Plan'!F3:F241,{"-","4"},'SCIMP Plan'!B3:B241,"*Purview*",'SCIMP Plan'!C3:C241,"Product"))} -> 16 | X49: Desired Features | Y49: {=SUM(COUNTIFS('SCIMP Plan'!F3:F241,{"1","2","3"},'SCIMP Plan'!B3:B241,"*Purview*",'SCIMP Plan'!C3:C241,"feature"))} -> 0
X50: Not assessed or no value | Y50: {=SUM(COUNTIFS('SCIMP Plan'!F3:F241,{"-","4"},'SCIMP Plan'!B3:B241,"*Purview*",'SCIMP Plan'!C3:C241,"feature"))} -> 11
B61: View of Microsoft 365 E3 Technologies (This section shows the value from E3 products and features as well as alignment to best practice configurations and processes)
D64: E3 Products | K64: E3 Features | S64: E3 Optional Configurations
D65: Realised value | E65: {=SUM(COUNTIFS('SCIMP Plan'!F3:F241,{"D","W"},'SCIMP Plan'!B3:B241,"*M365 E3*",'SCIMP Plan'!C3:C241,"Product"))} -> 0 | K65: Realised value | L65: {=SUM(COUNTIFS('SCIMP Plan'!F3:F241,{"D","W"},'SCIMP Plan'!B3:B241,"*M365 E3*",'SCIMP Plan'!C3:C241,"feature"))} -> 0 | S65: Realised value | T65: {=SUM(COUNTIFS('SCIMP Plan'!F3:F241,{"D","W"},'SCIMP Plan'!B3:B241,"*M365 E3*",'SCIMP Plan'!C3:C241,"Configuration") + COUNTIFS('SCIMP Plan'!F3:F241,{"D","W"},'SCIMP Plan'!B3:B241,"*M365 E3*",'SCIMP Plan'!C3:C241,"Consideration") + COUNTIFS('SCIMP Plan'!F3:F241,{"D","W"},'SCIMP Plan'!B3:B241,"*M365 E3*",'SCIMP Plan'!C3:C241,"Process") + COUNTIFS('SCIMP Plan'!F3:F241,{"D","W"},'SCIMP Plan'!B3:B241,"*M365 E3*",'SCIMP Plan'!C3:C241,"Suggestion"))} -> 0
D66: Desired Features | E66: {=SUM(COUNTIFS('SCIMP Plan'!F3:F241,{"1","2","3"},'SCIMP Plan'!B3:B241,"*M365 E3*",'SCIMP Plan'!C3:C241,"Product"))} -> 0 | K66: Desired Features | L66: {=SUM(COUNTIFS('SCIMP Plan'!F3:F241,{"1","2","3"},'SCIMP Plan'!B3:B241,"*M365 E3*",'SCIMP Plan'!C3:C241,"feature"))} -> 0 | S66: Desired Features | T66: {=SUM(COUNTIFS('SCIMP Plan'!F3:F241,{"1","2","3"},'SCIMP Plan'!B3:B241,"*M365 E3*",'SCIMP Plan'!C3:C241,"Configuration") + COUNTIFS('SCIMP Plan'!F3:F241,{"1","2","3"},'SCIMP Plan'!B3:B241,"*M365 E3*",'SCIMP Plan'!C3:C241,"Consideration") + COUNTIFS('SCIMP Plan'!F3:F241,{"1","2","3"},'SCIMP Plan'!B3:B241,"*M365 E3*",'SCIMP Plan'!C3:C241,"Process") + COUNTIFS('SCIMP Plan'!F3:F241,{"1","2","3"},'SCIMP Plan'!B3:B241,"*M365 E3*",'SCIMP Plan'!C3:C241,"Suggestion"))} -> 0
D67: Not assessed or no value | E67: {=SUM(COUNTIFS('SCIMP Plan'!F3:F241,{"-","4"},'SCIMP Plan'!B3:B241,"*M365 E3*",'SCIMP Plan'!C3:C241,"Product"))} -> 17 | K67: Not assessed or no value | L67: {=SUM(COUNTIFS('SCIMP Plan'!F3:F241,{"-","4"},'SCIMP Plan'!B3:B241,"*M365 E3*",'SCIMP Plan'!C3:C241,"feature"))} -> 41 | S67: Not assessed or no value | T67: {=SUM(COUNTIFS('SCIMP Plan'!F3:F241,{"-","4"},'SCIMP Plan'!B3:B241,"*M365 E3*",'SCIMP Plan'!C3:C241,"Configuration") + COUNTIFS('SCIMP Plan'!F3:F241,{"-","4"},'SCIMP Plan'!B3:B241,"*M365 E3*",'SCIMP Plan'!C3:C241,"Consideration") + COUNTIFS('SCIMP Plan'!F3:F241,{"-","4"},'SCIMP Plan'!B3:B241,"*M365 E3*",'SCIMP Plan'!C3:C241,"Process") + COUNTIFS('SCIMP Plan'!F3:F241,{"-","4"},'SCIMP Plan'!B3:B241,"*M365 E3*",'SCIMP Plan'!C3:C241,"Suggestion"))} -> 39
B79: Current State and Priorites of Solution Areas
C82: Identity | J82: Endpoints | Q82: Threat Protection | X82: Complaince
C83: Deployed | D83: =COUNTIF('SCIMP Plan'!F11:F73,"D") -> 0 | J83: Deployed | K83: =COUNTIF('SCIMP Plan'!F74:F123,"D") -> 0 | Q83: Deployed | R83: =COUNTIF('SCIMP Plan'!F124:F182,"D") -> 0 | X83: Deployed | Y83: =COUNTIF('SCIMP Plan'!F184:F241,"D") -> 0
C84: Work in Progress | D84: =COUNTIF('SCIMP Plan'!F11:F73,"W") -> 0 | J84: Work in Progress | K84: =COUNTIF('SCIMP Plan'!F74:F123,"W") -> 0 | Q84: Work in Progress | R84: =COUNTIF('SCIMP Plan'!F124:F182,"W") -> 0 | X84: Work in Progress | Y84: =COUNTIF('SCIMP Plan'!F184:F241,"W") -> 0
C85: High Priority | D85: =COUNTIF('SCIMP Plan'!F11:F73,"1") -> 0 | J85: High Priority | K85: =COUNTIF('SCIMP Plan'!F74:F123,"1") -> 0 | Q85: High Priority | R85: =COUNTIF('SCIMP Plan'!F124:F182,"1") -> 0 | X85: High Priority | Y85: =COUNTIF('SCIMP Plan'!F184:F241,"1") -> 0
C86: Medium Priority | D86: =COUNTIF('SCIMP Plan'!F11:F73,"2") -> 0 | J86: Medium Priority | K86: =COUNTIF('SCIMP Plan'!F74:F123,"2") -> 0 | Q86: Medium Priority | R86: =COUNTIF('SCIMP Plan'!F124:F182,"2") -> 0 | X86: Medium Priority | Y86: =COUNTIF('SCIMP Plan'!F184:F241,"2") -> 0
C87: Low Priority | D87: =COUNTIF('SCIMP Plan'!F11:F73,"3") -> 0 | J87: Low Priority | K87: =COUNTIF('SCIMP Plan'!F74:F123,"3") -> 0 | Q87: Low Priority | R87: =COUNTIF('SCIMP Plan'!F124:F182,"3") -> 0 | X87: Low Priority | Y87: =COUNTIF('SCIMP Plan'!F184:F241,"3") -> 0
C88: No intent or not yet assessed | D88: {=SUM(COUNTIFS('SCIMP Plan'!F11:F73,{"4","-"}))} -> 55 | J88: No intent or not yet assessed | K88: {=SUM(COUNTIFS('SCIMP Plan'!F74:F123,{"4","-"}))} -> 41 | Q88: No intent | R88: {=SUM(COUNTIFS('SCIMP Plan'!F124:F182,{"4","-"}))} -> 48 | X88: No intent or not yet assessed | Y88: {=SUM(COUNTIF('SCIMP Plan'!F184:F241,{"4","-"}))} -> 51
C97: Blue areas represent the deployed technologies for that solution area, this where you organisation has realised value
C98: Purple areas show "Work in Progress", representing the technologies your organization is currently deploying (in-flight), be that design stages, proof of concept, pilot or full deployment
C99: Green areas represent technologies where you organization sees a definite need (high value) and shows a high intent to deploy
C100: Amber areas represent technologies your organization sees value in but has prioritised higher value technologies over them (green areas)
C101: Red areas show technologies your organization sees value in but has been deprioritized to the level of risk they close off or require increased effort to deploy
C102: Greys areas are a combination of technologies where your organization cannot see value in the technologies at this time
B105: Cost of Deployment and Change
I107: This graph to help understand what resources are aligned to technolologies and configuration that are currently being deployed or prioritized technologies not yet deployed. For those with Unified Support contracts, the cost of deploying yourself (self), using FastTrack or using an engagement from Unified will already be sunk into existing agreements. There may be additional costs using partners. For those with Unified Support contracts, your aligned Customer Success Account Manager (CSAM) will support all areas of deployment, be that sharing documentation or aligning SMEs from Unified and FastTrack. The CSAM can also support with partner engagements, helping to ensure all services are kept on plan and on track.
C109: -
C110: Self | D110: =COUNTIF('SCIMP Plan'!L3:L241,"Self") -> 0
C111: FastTrack | D111: =COUNTIF('SCIMP Plan'!L3:L241,"FastTrack") -> 0
C112: Unified Engagements | D112: =COUNTIF('SCIMP Plan'!L3:L241,"Unified Engagements") -> 0
C113: CSA | D113: =COUNTIF('SCIMP Plan'!L3:L241,"CSA") -> 0
C114: ISD (MCS) | D114: =COUNTIF('SCIMP Plan'!L3:L241,"IDS (MCS)") -> 0
C115: Partner | D115: =COUNTIF('SCIMP Plan'!L3:L241,"Partner") -> 0
C116: Account Team
J117: Grey areas respresent technologies that can be deployed by your own teams and no additional help beyond following documentation is required
J118: Green areas are where FastTrack will be aligned to support your deployment teams. Whilst your team will be "hands on keyboard", FastTrack engineers can guide with problem solves and best practices
J119: Blue areas are where Unified Support can be engaged, this can be through proactive engagements or through the use of a Dedicated Service Engineer (DSE). Your CSAM will be able to advise on this
J120: Amber areas show where partners have been recommended. This maybe for more complex areas where professional services maybe required. These will be at additional costs*
J121: *Costs will be subject to agreement with your chosen partner

Sheet Maturity Matrix
F3: LEGEND:
G5: E3 technologies | J5: E5 Technologies | N5: Azure Subscription | Q5: Standalone Licensing
G7: Priority TBC | J7: Deployed | N7: Work in Progress | Q7: High Priority | T7: Medium Priority | X7: Low Priority | AB7: No intent to deploy
E10: Identity and access management | L10: Endpoints | S10: Threat Protection | Z10: Compliance and Governance
B11: Technical Maturity | D11: Advanced State
G12: Microsoft Entra Identity Protection | J12: Entra Identity Governance: Entitlement Packages | N12: Microsoft Defender Application Control | Q12: Web Content Filtering (MDE-MDCA) | U12: Microsoft Sentinel | X12: MDC - Microsoft Defender for Servers (P2) | AB12: Microsoft Purview Data Catalogue | AE12: Microsoft Priva
G14: Entra Identity Governance: Access Reviews | J14: MDCA: Session Controls | N14: Windows AutoPatch | Q14: Windows 365 | U14: MDC - Microsoft Defender for Storage | X14: MDC - Microsoft Defender for SQL | AB14: Microsoft Purview Data Mapping | AE14: Microsoft Purview Data Connectors
G16: Privilege Identity Management | J16: Privileged Access Management (Exchange) | N16: Advanced Endpoint Analytics | Q16: Endpoint Privilege Management | U16: MDC - Microsoft Defender for Containers | X16: MDC - Microsoft Defender for Key Vault | AB16: Microsoft Purview Insider Risk Management | AE16: Microsoft Purview Communication Compliance
G18: CA: Target Resources (Authenication Context) | J18: Microsoft Entra Permissions Management (CIEM) | U18: MDC - Microsoft Defender for Resource Manager | X18: MDC - Microsoft Defender for DNS | AB18: Trainable Classifers | AE18: Exact Data Match
U20: MDC - Microsoft Defender for App Service | X20: MDC - Microsoft Defender for Open Source DBs | AB20: Microsoft Purview Audit (Premium) | AE20: Microsoft Purview Double Key Encryption
U22: MDC - Microsoft Defender for IoT | X22: MDC - Microsoft Defender for DevOps | AB22: Microsoft Defender for Cloud Apps (Data Governance) | AE22: Microsoft Purview Customer Key
U24: Azure Firewall | X24: Azure Web Application Firewall
U26: Microsoft Defender Threat Intelligence | X26: Azure Front Door
U28: Safe Documents | X28: Microsoft Defender External Attack Surface Management
D30: Medium State
G31: Risk Sign-ins monitoring | J31: Microsoft Entra RBAC Configuration | N31: Microsoft Tunnel | Q31: Intune Tunnel for MAM | U31: Microsoft 365 Defender XDR | X31: Microsoft Threat Experts | AB31: Microsoft Purview Customer Lockbox | AE31: Microsoft Purview eDiscovery (Premium)
G33: Passwordless Authentication | J33: Microsoft Entra App Proxy | N33: ConfigMgr Co-Management Config | Q33: Management of Specialty Devices | U33: Defender for Identity | X33: Microsoft Defender for Cloud Apps (Threat) | AB33: Endpoint DLP | AE33: Microsoft Defender for Cloud Apps (Shadow IT)
G35: Entra ID - Third party SaaS Applications (SSO) | J35: Self Service Group Management | N35: Update ConfigMgr to Current Branch | Q35: Microsoft Defender Exploit Guard (ASR) | U35: Defender for Office 365 | X35: MDC - Microsoft Defender for Servers (P1) | AB35: Microsoft Purview Records Management | AE35: On-premises DLP
G37: HR System Integration | J37: Enable MFA for On-prem services (RADIUS) | N37: Microsoft Defender Application Guard (Edge) | Q37: ConfigMgr -Cloud Management Gateway | U37: MDE for iOS | X37: Attack Simulator v2 | AB37: Purview Labelling Scanner - Classify/Label/Protect | AE37: Teams Data Loss Prevention
G39: Dynamic User Groups | J39: CA: Continuous Access Evaluation | N39: BYOD - Intune Categories | Q39: BYOD: MDM Config (iOS Android) | U39: MDE for Windows Desktops | X39: MDE for Android | AB39: Microsoft Purview Information Protection: Auto Labelling | AE39: Microsoft Purview Compliance Manager
G41: Conditional Access Policies | J41: Process - Assess Secure Score | N41: BYOD: MAM Polices - Mobile OS | Q41: Process - Migrate Apps to Intune | U41: MDE policy configuration | X41: MDE for Mac OS | AB41: Azure Monitor | AE41: Office Message Encryption
G43: CA: Authentication Strength | N43: Windows Hello | Q43: Remote Help | U43: Azure Arc deployment | X43: Defender for Cloud CSPM | AB43: Azure Policy
N45: Endpoint Analytics | Q45: Autopilot Configuration | U45: Azure Bastion | X45: Azure DDoS Protection
D47: Base State
G48: CA: Target Resources (User Actions Device Reg.) | J48: Microsoft Entra Temporary Access Passwords | N48: Windows 10/11 Deployment | Q48: Windows Client Evergreen Plan (WUfB) | U48: Microsoft Defender Antivirus (MDE P1) | X48: Exchange Online Protection | AB48: Microsoft Purview Information Protection: Manual Labelling | AE48: Microsoft Purview Labelling Scanner (Discovery Only)
G50: Microsoft Entra MFA for all users | J50: Self Service Password Reset (SSPR) | N50: Microsoft Defender Credential Guard | Q50: Microsoft Defender System Guard | U50: Office 365 Antimalware Configuration | X50: Secure External Mailflow (TSL, DKIM, DMARC, SPF) | AB50: Microsoft Purview Data Loss Prevention | AE50: Microsoft Purview eDiscovery (Standard)
G52: Conditional Access: Network Assignment | J52: Disable Accounts not used in last 30 days | N52: Windows Firewall | Q52: BitLocker | U52: Do not allow anonymous calendar sharing | X52: Block Client forwarding rules | AB52: Microsoft Purview Data Liftcycle Management | AE52: Microsoft Purview Audit (Standard)
G54: Conditional Access: Block Legacy Auth | J54: Configure Application Consent for Data Access | N54: Corp: MAM Polices - Mobile OS | Q54: Corp: MDM Config (iOS Android) | U54: Transport rules: Block known ransomware files | X54: Configure Teams External Access (Federation) | AB54: Set Organization Level External Sharing settings | AE54: Define Sensitive Information Types
G56: CA: Target Resources (User Actions - Security info) | J56: Microsoft Entra Password Protection | N56: Base Line Compliance Policies | Q56: Corp: MDM Polices - Desktop OS | U56: Configure Teams Guest Access | AB56: Process - Define Classification Schema
G58: Identity Object Remediation | J58: Microsoft Entra Connect Deployment | N58: Unified Write Filter | Q58: Entra Domain Join or Hybrid Domain Join

Sheet SCIMP Plan
A1: Task Name | B1: License | C1: Line Type | D1: Predecessors | E1: NCSC Blueprint | F1: Priority | G1: RAG: Design and Planning | H1: RAG: Admin Configuration | I1: RAG: Deployment Time | J1: RAG: User Change (Impact) | K1: Comment | L1: Microsoft Resource Type | M1: Engagement Type | N1: Recommended use | O1: Key Stakeholder | P1: Risk Register / Audit Report Alignment | Q1: Existing Third party Product | R1: Contract End date | S1: Soft saving category | T1: Business Justification | U1: Resource Type | V1: Management Portal | W1: RBAC Role in Microsoft Entra ID | X1: One Tenant, Multi Organization Scope | Y1: Product Category | Z1: Zero Trust Pillar | AA1: Available with Unified Support (subject to contract) | AB1: Related Value Based Delivery (VBD) ? | AC1: Does the VBD belong to a Designated Engineering package (If so, which one) ? | AD1: Fasttrack Support Offering | AE1: SC Exam | AF1: ESI | AG1: MCAPS
A2: High Level Prerequisites | B2: __ | C2: __ | D2: __ | E2: __ | F2: __ | G2: __ | H2: __ | I2: __ | J2: __ | K2: __ | L2: __ | M2: __ | N2: __ | O2: __ | P2: __ | Q2: __ | R2: __ | S2: __ | T2: =IF(Config!$B$2='Data Validations'!$E$2,Text!B2,IF(Config!$B$2='Data Validations'!$E$3,Text!C2,"Select a lanaguage in config")) -> __ | U2: __ | V2: __ | W2: __ | X2: __ | Y2: __ | Z2: __ | AA2: __
A3: Identity object remediation | B3: M365 E3, M365 F3 | C3: Configuration | F3: - | L3: - | M3: - | N3: - | S3: Operational | T3: =IF(Config!$B$2='Data Validations'!$E$2,Text!B3,IF(Config!$B$2='Data Validations'!$E$3,Text!C3,"Select a lanaguage in config")) -> Allows for synchronisation of on-premises Active Directory accounts into Microsoft Entra ID | U3: Identity | V3: On-premises (ID Fix, dsa.msc) | W3: N/A (On-prem activity) | X3: Organization Specific (on-premises deployment) | Y3: Identity and Access Management | Z3: Identity | AA3: Yes | AD3: Core onboarding: Identity Integration; Microsoft Entra ID: Secure Foundation Infrastructure
A4: Microsoft Entra Connect Deployment (directory synchronization) | B4: M365 E3, M365 F3 | C4: Product | D4: =CONCATENATE(ROW(A3)) -> 3 | F4: - | L4: - | M4: - | N4: - | S4: Operational | T4: =IF(Config!$B$2='Data Validations'!$E$2,Text!B4,IF(Config!$B$2='Data Validations'!$E$3,Text!C4,"Select a lanaguage in config")) -> Creates a relationship between on-premises AD Accounts and AD accounts to make them appear as one account (single identity, effectively a hybrid identity) | U4: Identity, Server Infrastructure | V4: https://portal.azure.com for cloud provisioning | W4: Global Admin | X4: Scoped (Domain, OU, Group filtering) | Y4: Identity and Access Management | Z4: Identity | AA4: Yes | AB4: Onboarding Accelerator – Microsoft Entra ID: Features Deployment (Base) | AC4: Zero Trust: Identity | AD4: Core onboarding: Identity Integration; Microsoft Entra ID: Secure Foundation Infrastructure
A5: Recommended - Configure Password Hash Synchronisation | B5: M365 E3, M365 F3 | C5: Feature | D5: =CONCATENATE(ROW(A3)) -> 3 | E5: Good | F5: - | L5: - | M5: - | N5: - | S5: Productivity | T5: =IF(Config!$B$2='Data Validations'!$E$2,Text!B5,IF(Config!$B$2='Data Validations'!$E$3,Text!C5,"Select a lanaguage in config")) -> Allows for seamless single sign on whilst also removing the need for AD FS servers. This also means no reliance on any servers for authentication on-premises reducing surface area of attack | U5: Identity, Server Infrastructure | V5: On-premises configuration | W5: Global Admin | X5: Organization Specific (Domain Specific) | Y5: Identity and Access Management | Z5: Identity | AA5: Yes | AB5: Zero Trust Foundations Assessment | AC5: Zero Trust: Identity
A6: Microsoft Apps for Enterprise (Office ProPlus) | B6: M365 E3 | C6: Product | D6: =CONCATENATE(ROW(A4)) -> 4 | F6: - | L6: - | M6: - | N6: - | S6: Productivity | T6: =IF(Config!$B$2='Data Validations'!$E$2,Text!B6,IF(Config!$B$2='Data Validations'!$E$3,Text!C6,"Select a lanaguage in config")) -> Always latest and greatest version of Office deployed using the modern Click to Run method. | U6: End User Compute | V6: https://intune.microsoft.com/ | W6: N/A (On-prem activity) | X6: Organization Specific (on-premises deployment) | Y6: Productivity Suite | Z6: Applications | AA6: Yes | AD6: Microsoft 365 Apps; App Assure; Microsoft Teams
A7: Data Migration | B7: _ | C7: _ | D7: _ | E7: _ | F7: - | G7: _ | H7: _ | I7: _ | J7: _ | K7: _ | L7: _ | M7: _ | N7: _ | O7: _ | P7: _ | Q7: _ | R7: _ | S7: _ | T7: =IF(Config!$B$2='Data Validations'!$E$2,Text!B7,IF(Config!$B$2='Data Validations'!$E$3,Text!C7,"Select a lanaguage in config")) -> _ | U7: _ | V7: _ | W7: _ | X7: _ | Y7: _ | Z7: _ | AA7: _
A8: Exchange migration | B8: M365 E3, M365 F3 | C8: Product | D8: =CONCATENATE(ROW(A4)) -> 4 | F8: - | L8: - | M8: - | N8: - | S8: Operational, Productivity | T8: =IF(Config!$B$2='Data Validations'!$E$2,Text!B8,IF(Config!$B$2='Data Validations'!$E$3,Text!C8,"Select a lanaguage in config")) -> Significantly reduce or remove on-premises Exchange servers and all it's associated requirements leaving uses with an always up to date Exchange, access from anywhere, significantly larger mailboxes, transport rules and advanced compliance features on top of other benefits | U8: Active Directory, Exchange, Server infrastructure | V8: https://admin.microsoft.com | W8: Organization Management | X8: Scoped (Domain, OU, Group filtering) | Y8: Email | Z8: Applications | AA8: Yes
A9: SharePoint Migration | B9: M365 E3, M365 F3 | C9: Product | D9: =CONCATENATE(ROW(A4)) -> 4 | F9: - | L9: - | M9: - | N9: - | S9: Operational, Productivity | T9: =IF(Config!$B$2='Data Validations'!$E$2,Text!B9,IF(Config!$B$2='Data Validations'!$E$3,Text!C9,"Select a lanaguage in config")) -> Migrate from legacy file shares to modern document management with SharePoint Online, providing an EDRM system, structured data, better searching, larger storage capacity, better insights, secure access from anywhere and access to advanced compliance features on top of other benefits | U9: Information Governance, Storage, Solutions Architect | V9: https://admin.microsoft.com | W9: SharePoint Administrator | X9: Scoped (Domain, OU, Group filtering) | Y9: Document Management/Internet/EDRMS | Z9: Applications/Data | AA9: Yes | AB9: Activate SharePoint Online Migration MIP | AD9: SPO/ ODfB; Data Migration
A10: OneDrive Migration | B10: M365 E3, M365 F3 | C10: Product | D10: =CONCATENATE(ROW(A4)) -> 4 | F10: - | L10: - | M10: - | N10: - | S10: Operational, Productivity | T10: =IF(Config!$B$2='Data Validations'!$E$2,Text!B10,IF(Config!$B$2='Data Validations'!$E$3,Text!C10,"Select a lanaguage in config")) -> Migrate from legacy home drives to modern document management with OneDrive for Business, providing an EDRM system, structured data, better searching, unlimited storage capacity, secure access from anywhere and access to advanced compliance features on top of other benefits | U10: Information Governance, Storage, Solutions Architect | V10: https://admin.microsoft.com | W10: SharePoint Administrator | X10: Scoped (Domain, OU, Group filtering) | Y10: Document Management/Internet/EDRMS | Z10: Applications/Data | AA10: Yes | AD10: SPO/ ODfB; Data Migration
A11: Identity (Microsoft Entra) | B11: __ | C11: __ | D11: __ | E11: __ | F11: __ | G11: __ | H11: __ | I11: __ | J11: __ | K11: __ | L11: __ | M11: __ | N11: __ | O11: __ | P11: __ | Q11: __ | R11: __ | S11: __ | T11: =IF(Config!$B$2='Data Validations'!$E$2,Text!B11,IF(Config!$B$2='Data Validations'!$E$3,Text!C11,"Select a lanaguage in config")) -> __ | U11: __ | V11: __ | W11: __ | X11: __ | Y11: __ | Z11: __ | AA11: __
A12: Strong Authentication | B12: _ | C12: _ | D12: _ | E12: _ | F12: _ | G12: _ | H12: _ | I12: _ | J12: _ | K12: _ | L12: _ | M12: _ | N12: _ | O12: _ | P12: _ | Q12: _ | R12: _ | S12: _ | T12: =IF(Config!$B$2='Data Validations'!$E$2,Text!B12,IF(Config!$B$2='Data Validations'!$E$3,Text!C12,"Select a lanaguage in config")) -> _ | U12: _ | V12: _ | W12: _ | X12: _ | Y12: _ | Z12: _ | AA12: _ | AB12: WorkshopPLUS - Microsoft Azure: Identity | AC12: Zero Trust: Identity
A13: Microsoft Entra Password Protection | B13: M365 E3, M365 F3 | C13: Feature | D13: =CONCATENATE(ROW(A4)) -> 4 | E13: Good | F13: - | L13: - | M13: - | N13: - | S13: Risk Reduction | T13: =IF(Config!$B$2='Data Validations'!$E$2,Text!B13,IF(Config!$B$2='Data Validations'!$E$3,Text!C13,"Select a lanaguage in config")) -> Stops users from using common passwords and forces them (politely) to set not a only a complex password but one that is more unique and less guessable. In turn this, coupled with MFA, removes the need for users to changes their passwords on a regular basis. This can help reduce load on the helpdesk for forgotten passwords or users physically writing down passwords and taping to desks | U13: Identity, Server Infrastructure | V13: https://entra.microsoft.com | W13: Security Administrator | X13: Tenant Wide | Y13: Identity and Access Management | Z13: Identity | AA13: Yes | AC13: Zero Trust: Identity | AD13: Microsoft Entra ID: Secure Foundation Infrastructure
A14: Microsoft Entra Conditional Access: Network Assignment | B14: M365 E3, M365 F3 | C14: Configuration | D14: =CONCATENATE(ROW(A4)) -> 4 | E14: Good | F14: - | L14: - | M14: - | N14: - | S14: Risk Reduction | T14: =IF(Config!$B$2='Data Validations'!$E$2,Text!B14,IF(Config!$B$2='Data Validations'!$E$3,Text!C14,"Select a lanaguage in config")) -> This has less of a use case in Zero Trust, but can still be used to help validate users when setting up MFA or enrolling devices. I.e., they must pass through physical security before setting up digital security | U14: Identity, Networking | V14: https://entra.microsoft.com | W14: Conditional Access Administrator | X14: Scoped (named locations) | Y14: Identity and Access Management | Z14: Identity | AA14: Yes | AC14: Zero Trust: Identity | AD14: Microsoft Entra ID: Secure Foundation Infrastructure
A15: Microsoft Entra Conditional Access: Target Resources (User Actions - register security information) | B15: M365 E3, M365 F3 | C15: Configuration | D15: =CONCATENATE(ROW(A4)) -> 4 | E15: Good | F15: - | L15: - | M15: - | N15: - | S15: Risk Reduction | T15: =IF(Config!$B$2='Data Validations'!$E$2,Text!B15,IF(Config!$B$2='Data Validations'!$E$3,Text!C15,"Select a lanaguage in config")) -> Allows organizations to define the conditional access conditions a user must go through to enrol into MFA or Self Service Password Reset (SSPR). This helps validate the user is a member of the organization and not an attacker with phished credentials creating trust through MFA | U15: Identity | V15: https://entra.microsoft.com | W15: Conditional Access Administrator | X15: Scoped (to CA policy) | Y15: Identity and Access Management | Z15: Identity | AA15: Yes | AC15: Zero Trust: Identity | AD15: Microsoft Entra ID: Secure Foundation Infrastructure
A16: Microsoft Entra MFA for all users (ZT: Strong Authentication) | B16: M365 E3, M365 F3 | C16: Feature | D16: =CONCATENATE(ROW(A4)) -> 4 | E16: Good | F16: - | L16: - | M16: - | N16: - | S16: Risk Reduction | T16: =IF(Config!$B$2='Data Validations'!$E$2,Text!B16,IF(Config!$B$2='Data Validations'!$E$3,Text!C16,"Select a lanaguage in config")) -> Stops 99.9% of Identity based attacks. As identity is the control plane, MFA is essential protection. Factors of authentication are broken down into something you know (password/PIN), something you have (i.e. phone or token) and something you are (biometrics). The latter two typically can only exist in one place at a time giving trust that the user who provides these is who they claim to be. | U16: Identity, Helpdesk, End User Compute | V16: https://entra.microsoft.com | W16: Authentication Administrator | X16: Organization Specific (Administrative Units) | Y16: Identity and Access Management | Z16: Identity | AA16: Yes | AC16: Zero Trust: Identity | AD16: Microsoft Entra ID: Secure Foundation Infrastructure
A17: Microsoft Entra Combined Registration (SSPR and MFA-R) | B17: M365 E3, M365 F3 | C17: Feature | D17: =CONCATENATE(ROW(A16)) -> 16 | F17: - | L17: - | M17: - | N17: - | S17: Operational, Risk Reduction, Productivity | T17: =IF(Config!$B$2='Data Validations'!$E$2,Text!B17,IF(Config!$B$2='Data Validations'!$E$3,Text!C17,"Select a lanaguage in config")) -> Can significantly reduce load on the help desk by allowing users to reset their own passwords. Provides greater levels of validation that the user is who they claim to be through MFA when resetting passwords. Also allows a user to reset their password anytime, even outside of helpdesk operating hours. Can also be used as a response action, in line with Azure Identity Protection, to help remediate compromised accounts | U17: Identity, Helpdesk, End User Compute | V17: https://entra.microsoft.com | W17: User Administrator + Global Administrator | X17: Tenant wide settings, scoped deployment | Y17: Identity and Access Management | Z17: Identity | AA17: Yes | AC17: Zero Trust: Identity | AD17: Microsoft Entra ID: Secure Foundation infrastructure; Microsoft Entra ID: Automation & Efficiencies
A18: Microsoft Entra Temporary Access Passwords | B18: M365 E3, M365 F3 | C18: Feature | D18: =CONCATENATE(ROW(A4)) -> 4 | E18: Good | F18: - | L18: - | M18: - | N18: - | S18: Operational | T18: =IF(Config!$B$2='Data Validations'!$E$2,Text!B18,IF(Config!$B$2='Data Validations'!$E$3,Text!C18,"Select a lanaguage in config")) -> Primarily used by users go passwordless by validating them as a member of your organization before they setup a passwordless token. In the same vain this can be used to setup MFA for users who cannot come to site or do not yet have a trusted device to setup MFA from. This can also be used as a "get out of jail free card" for users who have "forgotten" MFA devices but not lost them so they can still work for the day. | U18: Identity | V18: https://entra.microsoft.com | W18: Authentication Administrator | X18: Organization Specific (Administrative Units) | Y18: Identity and Access Management | Z18: Identity | AA18: Yes | AC18: Zero Trust: Identity
A19: Passwordless Authentication (ZT: Strong Authentication) | B19: M365 E3, M365 F3 | C19: Feature | D19: =CONCATENATE(ROW(A4)) -> 4 | E19: Good | F19: - | L19: - | M19: - | N19: - | S19: Risk Reduction, Productivity | T19: =IF(Config!$B$2='Data Validations'!$E$2,Text!B19,IF(Config!$B$2='Data Validations'!$E$3,Text!C19,"Select a lanaguage in config")) -> Removes legacy passwords and provides strong, user friendly, non-phishable credentials. The future of authentication | U19: Identity, Helpdesk, End User Compute | V19: https://entra.microsoft.com | W19: Security Administrator + Global Admin | X19: Tenant wide settings, scoped deployment | Y19: Identity and Access Management | Z19: Identity | AA19: Yes | AC19: Zero Trust: Identity
A20: Microsoft Entra Authentication Methods: Certificate-Based Authentication | B20: M365 E3, M365 F3 | C20: Feature | D20: =CONCATENATE(ROW(A4)) -> 4 | F20: - | L20: - | M20: - | N20: - | S20: Operational, Risk Reduction, Productivity | T20: =IF(Config!$B$2='Data Validations'!$E$2,Text!B20,IF(Config!$B$2='Data Validations'!$E$3,Text!C20,"Select a lanaguage in config")) -> Microsoft Entra certificate-based authentication (CBA) enables organizations to configure their Microsoft Entra tenants to allow or require users to authenticate with X.509 certificates created by their Enterprise Public Key Infrastructure (PKI) for app and browser sign-in. This method of authentication is cost effective and secure alterative for users who refuse to use their own device for MFA and cannot be provide with a corporate phone. CBA should also be considered for workload identities. | W20: Global Admin | Y20: Identity and Access Management | Z20: Identity
A21: Microsoft Entra Authentication Methods: OATH Tokens (Preview for HW tokens) | B21: M365 E3, M365 F3 | C21: Feature | D21: =CONCATENATE(ROW(A5)) -> 5 | F21: - | L21: - | M21: - | N21: - | S21: Operational, Risk Reduction, Productivity | T21: =IF(Config!$B$2='Data Validations'!$E$2,Text!B21,IF(Config!$B$2='Data Validations'!$E$3,Text!C21,"Select a lanaguage in config")) -> This hardware OATH token preview improves flexibility and security for organizations by removing Global Administrator requirements. Organizations can delegate token creation, assignment, and activation to Privileged Authentication Administrators or Authentication Policy Administrators. | V21: https://entra.microsoft.com | W21: Authentication Administrator | Y21: Identity and Access Management | Z21: Identity
A22: Microsoft Entra Verified ID | B22: M365 E3, M365 F3, Entra Suite for Face Checks | C22: Product | F22: - | L22: - | M22: - | N22: - | S22: Risk Reduction, Productivity | T22: =IF(Config!$B$2='Data Validations'!$E$2,Text!B22,IF(Config!$B$2='Data Validations'!$E$3,Text!C22,"Select a lanaguage in config")) -> We believe a standards-based Decentralized Identity system can unlock a new set of experiences that give users and organizations greater control over their data—and deliver a higher degree of trust and security for apps, devices, and service providers. | V22: https://entra.microsoft.com | W22: Authentication Administrator | Y22: Identity and Access Management | Z22: Identity
A23: Suggestion - Enable Microsoft Entra MFA for On-prem services (RADIUS) | B23: M365 E3, M365 F3 | C23: Suggestion | D23: =CONCATENATE(ROW(A16)) -> 16 | F23: - | L23: - | M23: - | N23: - | S23: Operational | T23: =IF(Config!$B$2='Data Validations'!$E$2,Text!B23,IF(Config!$B$2='Data Validations'!$E$3,Text!C23,"Select a lanaguage in config")) -> Allows users to use the same additional factors of authentication they use with Azure MFA for on-premises services, such as VPNs and RDP access. Reduces the need to have yet more MFA tokens or other MFA services. | U23: Server infrastructure, Identity, Helpdesk, End User Compute | V23: On-premises configuration | W23: Authentication Policy Administrator | X23: Organization Specific (on-premises deployment) | Y23: Identity and Access Management | Z23: Identity/Applications | AA23: Yes | AC23: Zero Trust: Identity
A24: Conditional Access | B24: _ | C24: _ | D24: _ | E24: _ | F24: _ | G24: _ | H24: _ | I24: _ | J24: _ | K24: _ | L24: _ | M24: _ | N24: _ | O24: _ | P24: _ | Q24: _ | R24: _ | S24: _ | T24: =IF(Config!$B$2='Data Validations'!$E$2,Text!B24,IF(Config!$B$2='Data Validations'!$E$3,Text!C24,"Select a lanaguage in config")) -> _ | U24: _ | V24: _ | W24: _ | X24: _ | Y24: _ | Z24: _ | AA24: _ | AB24: Activate Azure with Multi-Factor Authentication and Conditional Access | AC24: Zero Trust: Identity
A25: Microsoft Entra Conditional Access: Block Legacy Authentication | B25: M365 E3, M365 F3 | C25: Configuration | D25: =CONCATENATE(ROW(A4),",",ROW(A6),",",ROW(A16)) -> 4,6,16 | E25: Good | F25: - | L25: - | M25: - | N25: - | S25: Risk Reduction | T25: =IF(Config!$B$2='Data Validations'!$E$2,Text!B25,IF(Config!$B$2='Data Validations'!$E$3,Text!C25,"Select a lanaguage in config")) -> Reduces surface area of attacks and stops the use of weak authentication methods that does not support MFA (strong authentication). Allowing legacy authentication in any capacity should be highlight on your risk register | U25: Identity, Security | V25: https://entra.microsoft.com | W25: Conditional Access Administrator | X25: Scoped (to CA policy) | Y25: Identity and Access Management | Z25: Identity/Applications | AA25: Yes | AC25: Zero Trust: Identity
A26: Microsoft Entra Conditional Access: Policies | B26: M365 E3, M365 F3 | C26: Feature | D26: =CONCATENATE(ROW(A16)) -> 16 | E26: Good | F26: - | L26: - | M26: - | N26: - | S26: Risk Reduction, Operational | T26: =IF(Config!$B$2='Data Validations'!$E$2,Text!B26,IF(Config!$B$2='Data Validations'!$E$3,Text!C26,"Select a lanaguage in config")) -> The cornerstone of modern authentication providing adaptive access controls based on users, devices, applications, data and risk. Effectively ensuring that right users have the right level of access based on the levels of controls they can adhere to. i.e., users on a fully managed device and MFA can access rich clients and download data whilst users on unmanaged (BYOPC) devices can be restricted to the browser and session controls can extraction of data) | U26: Identity, Security | V26: https://entra.microsoft.com | W26: Conditional Access Administrator | X26: Scoped (to CA policy) | Y26: Identity and Access Management | Z26: Identity | AA26: Yes | AC26: Zero Trust: Identity | AD26: Microsoft Entra ID: Secure Foundation Infrastructure
A27: Microsoft Entra Identity Protection | B27: M365 Defender Suite, M365 Defender Suite FLW | C27: Product | D27: =CONCATENATE(ROW(A17),",",ROW(A26)) -> 17,26 | E27: Better | F27: - | L27: - | M27: - | N27: - | S27: Risk Reduction, Operational | T27: =IF(Config!$B$2='Data Validations'!$E$2,Text!B27,IF(Config!$B$2='Data Validations'!$E$3,Text!C27,"Select a lanaguage in config")) -> Add risks as a condition to conditional access. Not only can this help work towards your Zero Trust strategy. For example, if risk is set to low with a requirement for MFA for all users, they will get additional MFA prompts. As they build a pattern of behaviour within the service (only seen by the A.I. / ML engines), and conform to this pattern they will be challenged for MFA less and less. This can help improve the user experience (less MFA prompts) whilst maintaining a high level of security. | U27: Identity, Security | V27: https://entra.microsoft.com | W27: Security Administrator | X27: Scoped (to CA policy) | Y27: Identity and Access Management | Z27: Identity | AA27: Yes | AC27: Zero Trust: Identity | AD27: Microsoft Entra ID: Secure Foundation Infrastructure
A28: Microsoft Defender for Cloud Apps (Session Controls) | B28: M365 Defender Suite, M365 Purview Suite, M365 Defender Suite FLW | C28: Product | D28: =CONCATENATE(ROW(A26)) -> 26 | E28: Best | F28: - | L28: - | M28: - | N28: - | S28: Risk Reduction, Operational | T28: =IF(Config!$B$2='Data Validations'!$E$2,Text!B28,IF(Config!$B$2='Data Validations'!$E$3,Text!C28,"Select a lanaguage in config")) -> Brings more control for BYOD (especially BOYPC) and external users. Limits sessions on unmanaged devices to browser, controlling/blocking the transfer of data in and out of your environment | U28: Identity, Security, End User Compute | V28: https://security.microsoft.com | W28: Security Administrator | X28: Scoped (to CA policy) | Y28: Identity and Access Management | Z28: Identity | AA28: Yes | AC28: Zero Trust: Identity
A29: Assess Continuous Access Evaluation | B29: M365 E3, M365 F3 | C29: Configuration | D29: =CONCATENATE(ROW(A26)) -> 26 | F29: - | L29: - | M29: - | N29: - | S29: Risk Reduction | T29: =IF(Config!$B$2='Data Validations'!$E$2,Text!B29,IF(Config!$B$2='Data Validations'!$E$3,Text!C29,"Select a lanaguage in config")) -> Continuously re-evaluates access, enforcing conditional access controls when there is a change (such as a user moving from a trusted location to an untrusted one) rather than relying on session timeouts. Greatly improves security without impacting user experience | V29: https://entra.microsoft.com | W29: Conditional Access Administrator | X29: Scoped (Users and Groups) | Y29: Identity and Access Management | Z29: Identity | AA29: Yes
A30: Microsoft Entra Conditional Access: Target Resources (User Actions - register Device) | B30: M365 E3, M365 F3 | C30: Configuration | D30: =CONCATENATE(ROW(A16)) -> 16 | E30: Good | F30: - | L30: - | M30: - | N30: - | S30: Risk Reduction | T30: =IF(Config!$B$2='Data Validations'!$E$2,Text!B30,IF(Config!$B$2='Data Validations'!$E$3,Text!C30,"Select a lanaguage in config")) -> Provide the conditions under which a user can register a device into Microsoft Entra ID, such as being in a trusted location or requiring MFA - this helps ensure that is a user of your organization enrolling a device and not an attacker trying to gain device trust. | U30: Identity, End User Compute | V30: https://entra.microsoft.com | W30: Authentication Policy Administrator | X30: Tenant Wide | Y30: Identity and Access Management/Device Management | Z30: Identity/Devices | AA30: Yes | AB30: Zero Trust Foundations Assessment | AC30: Zero Trust: Identity | AD30: Intune MAM/MDM/Cloud Attach; Windows 10/11
A31: Microsoft Entra Conditional Access: Authentication Strength | B31: M365 E3, M365 F3 | C31: Configuration | D31: =CONCATENATE(ROW(A16),",",ROW(A26),", OPT:",ROW(A19)) -> 16,26, OPT:19 | F31: - | L31: - | M31: - | N31: - | S31: Risk Reduction, Operational | T31: =IF(Config!$B$2='Data Validations'!$E$2,Text!B31,IF(Config!$B$2='Data Validations'!$E$3,Text!C31,"Select a lanaguage in config")) -> Authentication strength can be set in the grant controls of a conditional access policy. This allows your organization to use stronger authentication methods for more sensitive applications. When used with Authentication Context, your organization can require more strict identity verification for access to specific data. | V31: https://entra.microsoft.com | W31: Conditional Access Administrator | X31: Scoped (to CA policy) | Y31: Identity and Access Management | Z31: Identity | AA31: Yes
A32: Microsoft Entra Conditional Access: Target Resources (Authentication Context) | B32: M365 E3, M365 F3 | C32: Configuration | D32: =CONCATENATE(ROW(A26),",", ROW(A31),",",ROW(A188)," OR ",ROW(A189)) -> 26,31,188 OR 189 | F32: - | L32: - | M32: - | N32: - | S32: Operational, Risk Reduction, Productivity | T32: =IF(Config!$B$2='Data Validations'!$E$2,Text!B32,IF(Config!$B$2='Data Validations'!$E$3,Text!C32,"Select a lanaguage in config")) -> Authentication Context allows you set strict or heavily defined security controls over specific applications and data. For example, users, including guests, can be accessing data in a SharePoint site, but some data might be more sensitive. When applying a label with protection (RMS encryption), this block access to the data in Line of Business applications or break processes. With Authentication context, the access to the data can restricted in Conditional Access. For example, when accessing the specific data within the SharePoint site, the Conditional Access policy may require a compliant device or a stronger Authentication Strength to access. In turn, this can reduce the number of conditional access policies required to great the equivalent level of granular access. | V32: https://entra.microsoft.com and https://compliance.microsoft.com | W32: Conditional Access Administrator | X32: Scoped (to CA policy and Information Protection Label) | Y32: Identity and Access Management | Z32: Identity | AA32: Yes
A33: Microsoft Entra Conditional Access: Workload Identities | B33: Entra Workload Identities Premium | C33: Configuration | F33: - | L33: - | M33: - | N33: - | S33: Operational, Productivity | T33: =IF(Config!$B$2='Data Validations'!$E$2,Text!B33,IF(Config!$B$2='Data Validations'!$E$3,Text!C33,"Select a lanaguage in config")) -> Conditional Access for workload identities enables blocking service principals: from outside of known public IP ranges, based on risk detected by Microsoft Entra ID Protection, in combination with authentication contexts. | W33: Conditional Access Administrator | X33: Scoped (to CA policy) | Y33: Identity and Access Management | Z33: Identity | AA33: Yes
A34: Global Secure Access: Microsoft Entra Internet Access - Universal Conditional Access | B34: Entra Suite | C34: Product | D34: =CONCATENATE(ROW(A26)) -> 26 | F34: - | L34: - | M34: - | N34: - | S34: Risk Reduction, Operational | T34: =IF(Config!$B$2='Data Validations'!$E$2,Text!B34,IF(Config!$B$2='Data Validations'!$E$3,Text!C34,"Select a lanaguage in config")) -> In addition to sending traffic to Global Secure Access, administrators can use Conditional Access policies to secure traffic profiles. They can mix and match controls as needed like requiring multifactor authentication, requiring a compliant device, or defining an acceptable sign-in risk. Applying these controls to network traffic not just cloud applications allows for what we call universal Conditional Access. | W34: Global Secure Access Administrator role | X34: Scoped (to CA policy) | Y34: Security Service Edge | Z34: Identity | AA34: Yes
A35: Suggestion - SME Review Conditional Access Policies | B35: N/A | C35: Suggestion | D35: =CONCATENATE(ROW(A26)) -> 26 | F35: - | L35: - | M35: - | N35: - | S35: Operational, Risk Reduction | T35: =IF(Config!$B$2='Data Validations'!$E$2,Text!B35,IF(Config!$B$2='Data Validations'!$E$3,Text!C35,"Select a lanaguage in config")) -> Conditional Access is your frontline for access into your environment, having professional services review and refine your policies can improve your security posture, ensure you are taking a modern approach and potentially improve the end user experience. | U35: External | V35: N/A | W35: N/A | Y35: Professional Services | AA35: Yes | AC35: Zero Trust: Identity
A36: Privilege Management (Cloud Administrators) | B36: _ | C36: _ | D36: _ | E36: _ | F36: _ | G36: _ | H36: _ | I36: _ | J36: _ | K36: _ | L36: _ | M36: _ | N36: _ | O36: _ | P36: _ | Q36: _ | R36: _ | S36: _ | T36: =IF(Config!$B$2='Data Validations'!$E$2,Text!B36,IF(Config!$B$2='Data Validations'!$E$3,Text!C36,"Select a lanaguage in config")) -> _ | U36: _ | V36: _ | W36: _ | X36: _ | Y36: _ | Z36: _ | AA36: _ | AB36: Architectural Service - Microsoft Entra ID: Designing a Secure Cloud Identity | AC36: Zero Trust: Identity
A37: Microsoft Entra RBAC Configuration (ZT: Least Privilege) | B37: M365 E3, M365 F3 | C37: Configuration | D37: =CONCATENATE(ROW(A4)) -> 4 | E37: Good | F37: - | L37: - | M37: - | N37: - | S37: Risk Reduction | T37: =IF(Config!$B$2='Data Validations'!$E$2,Text!B37,IF(Config!$B$2='Data Validations'!$E$3,Text!C37,"Select a lanaguage in config")) -> Following the Zero Trust principal of least privilege, granting your admins only the permissions they require can reduce the impact of breach, both from external attackers and insider threats | U37: Identity, Security, Information Governance | V37: All portals | W37: More information | X37: Scoped (Users and Groups) | Y37: Privileged Access | Z37: Identity | AA37: Yes | AC37: Zero Trust: Identity
A38: Microsoft Entra Privileged Identity Management (ZT: Least Privilege) | B38: M365 Defender Suite, M365 Defender Suite FLW | C38: Product | D38: =CONCATENATE(ROW(A4),",",ROW(A16)) -> 4,16 | E38: Better | F38: - | L38: - | M38: - | N38: - | S38: Risk Reduction | T38: =IF(Config!$B$2='Data Validations'!$E$2,Text!B38,IF(Config!$B$2='Data Validations'!$E$3,Text!C38,"Select a lanaguage in config")) -> Removes privileged standing access and provides auditing and justification around the use of privilege for both internal admins and external support (such as contractors). This significantly reduces your surface area of attack and the damage that can be done in a breach scenario | U38: Identity, Security | V38: https://entra.microsoft.com | W38: Privileged Role Administrator | X38: Scoped (Users and Groups) | Y38: Privileged Access | Z38: Identity | AA38: Yes | AC38: Zero Trust: Identity | AD38: Microsoft Entra ID: Governance
A39: Privileged Access Management (Exchange Online Only) | B39: M365 Defender Suite, M365 Purview Suite, M365 Defender Suite FLW | C39: Product | D39: =CONCATENATE(ROW(A4),",",ROW(A8),",",ROW(A37)) -> 4,8,37 | E39: Better | F39: - | L39: - | M39: - | N39: - | S39: Risk Reduction | T39: =IF(Config!$B$2='Data Validations'!$E$2,Text!B39,IF(Config!$B$2='Data Validations'!$E$3,Text!C39,"Select a lanaguage in config")) -> Provides additional auditing and justification around the most dangerous tasks (such as new-journalrule) that an Exchange admin can run. | U39: Identity, Security, Information Governance | V39: https://admin.microsoft.com | W39: Organization Management | X39: Scoped (Users and Groups) | Y39: Privileged Access | Z39: Identity/Applications | AA39: Yes | AC39: Zero Trust: Identity | AD39: N/A
A40: Conditional Access: Microsoft Admin Portals and Device filters | B40: M365 E3, M365 F3 | C40: Configuration | D40: =CONCATENATE(ROW(A4),",",ROW(A26)) -> 4,26 | F40: - | L40: - | M40: - | N40: - | S40: Operational, Risk Reduction | T40: =IF(Config!$B$2='Data Validations'!$E$2,Text!B40,IF(Config!$B$2='Data Validations'!$E$3,Text!C40,"Select a lanaguage in config")) -> Administrators can add any Microsoft Entra registered application to Conditional Access policies. | U40: Identity, Security | V40: https://entra.microsoft.com | W40: Conditional Access Administrator | X40: Scoped (Users or devices) | Y40: Identity and Access Management | Z40: Identity/Devices | AA40: Yes
A41: Microsoft Entra Workload Identities Premium | B41: Entra Workload Identities Premium | C41: Product | D41: =CONCATENATE(ROW(A129),",",ROW(A36)) -> 129,36 | F41: - | L41: - | M41: - | N41: - | S41: Operational, Risk Reduction | T41: =IF(Config!$B$2='Data Validations'!$E$2,Text!B41,IF(Config!$B$2='Data Validations'!$E$3,Text!C41,"Select a lanaguage in config")) -> Secures and governs workload identities (apps, service principals, managed identities) as the successor to Entra Permissions Management. Enables Conditional Access, identity risk detection, access reviews, and health insights for non‑human identities, reducing over‑privileged access and securing automated workloads such as CI/CD and service-to-service access. | U41: Identity, Security | V41: https://entra.microsoft.com | W41: Billing Administrator | X41: Scoped (Users, workloads, apps, cloud) | Y41: Identity and Access Management | Z41: Identity/Applications | AA41: Yes | AC41: Zero Trust: Identity
A42: Agent Identity, Lifecycle & Runtime Governance (Agent 365) | B42: Agent 365, M365 E7 | C42: Product | D42: =CONCATENATE(ROW(A4),",",ROW(A26)) -> 4,26 | F42: - | L42: - | M42: - | N42: - | S42: Risk Reduction, Operational | T42: =IF(Config!$B$2='Data Validations'!$E$2,Text!B42,IF(Config!$B$2='Data Validations'!$E$3,Text!C42,"Select a lanaguage in config")) -> AI agents act autonomously across data, apps, and workflows, creating new risk if over‑privileged. Agent 365 treats agents as first‑class identities with Microsoft Entra Agent ID, enforcing least privilege, Conditional Access, and lifecycle ownership. Organizations limit blast radius, prevent persistent access, and meet audit and regulatory expectations as agents scale. | U42: Identity | V42: https://entra.microsoft.com and https://admin.microsoft.com | W42: Security Administrator, AI Administrator | X42: Scoped (Users, Brower Plugins, Groups, AI tooling) and Tenant Wide | Y42: AI Identity Management | Z42: Identity | AA42: Yes | AC42: Zero Trust: Identity
A43: Agent Access Governance (Policy + Enforcement) | B43: M365 E7 | C43: Product, Features (Entra ID, Conditional Access, PIM) | D43: =CONCATENATE(ROW(A4),",",ROW(A26),",",ROW(A38)) -> 4,26,38 | F43: - | L43: - | M43: - | N43: - | S43: Risk Reduction, Operational | T43: =IF(Config!$B$2='Data Validations'!$E$2,Text!B43,IF(Config!$B$2='Data Validations'!$E$3,Text!C43,"Select a lanaguage in config")) -> Extends identity governance to AI agents and copilots, ensuring all non-human actors operate under controlled identities, enforced access policies, and least privilege. Reduces risk of unauthorized access, privilege escalation, and uncontrolled automation by introducing policy-based enforcement, lifecycle governance, and continuous monitoring of agent activity across the enterprise. | U43: Identity | V43: https://entra.microsoft.com and https://admin.microsoft.com | W43: Security Administrator, AI Administrator | X43: Scoped (Users, Brower Plugins, Groups, AI tooling) and Tenant Wide | Y43: AI Identity Management | Z43: Identity | AA43: Yes | AC43: Zero Trust: Identity
A44: Application Access and Security Service Edge Services (SSE) | B44: _ | C44: _ | D44: _ | E44: _ | F44: _ | G44: _ | H44: _ | I44: _ | J44: _ | K44: _ | L44: _ | M44: _ | N44: _ | O44: _ | P44: _ | Q44: _ | R44: _ | S44: _ | T44: =IF(Config!$B$2='Data Validations'!$E$2,Text!B44,IF(Config!$B$2='Data Validations'!$E$3,Text!C44,"Select a lanaguage in config")) -> _ | U44: _ | V44: _ | W44: _ | X44: _ | Y44: _ | Z44: _ | AA44: _ | AB44: WorkshopPLUS - Microsoft Azure: Identity | AC44: Zero Trust: Identity
A45: Configure Application Consent for Data Access | B45: M365 E3, M365 F3 | C45: Configuration | D45: =CONCATENATE(ROW(A4)) -> 4 | E45: Good | F45: - | L45: - | M45: - | N45: - | S45: Risk Reduction | T45: =IF(Config!$B$2='Data Validations'!$E$2,Text!B45,IF(Config!$B$2='Data Validations'!$E$3,Text!C45,"Select a lanaguage in config")) -> Reduces expose of potential PII data and gives control to admins who can grant consent if needed | U45: Identity | V45: https://entra.microsoft.com | W45: Global Admin | X45: Tenant Wide | Y45: Identity and Access Management | Z45: Applications | AA45: Yes | AC45: Zero Trust: Identity
A46: Microsoft Entra Application Proxy | B46: M365 E3, M365 F3 | C46: Product | D46: =CONCATENATE(ROW(A26)) -> 26 | F46: - | L46: - | M46: - | N46: - | S46: Operational, Risk Reduction, Productivity | T46: =IF(Config!$B$2='Data Validations'!$E$2,Text!B46,IF(Config!$B$2='Data Validations'!$E$3,Text!C46,"Select a lanaguage in config")) -> Can remove the need for VPNs by providing access to on-premises applications via Microsoft Entra ID (including Conditional Access, MFA, Identity Governance etc.). Outbound only connections significantly reducing your surface area of attack. Follows Zero trust application principals of verifying each connection to each application (rather than a VPN granting access to all applications and the internal network) | U46: Identity, End User Compute, Networking | V46: https://entra.microsoft.com | W46: Application Administrator | X46: Scoped (on-premises install / connector Groups) | Y46: Identity and Access Management | Z46: Applications | AA46: Yes | AC46: Zero Trust: Identity
A47: Microsoft Tunnel | B47: Azure Subscription, Intune Plan 1 | C47: Product | D47: =CONCATENATE(ROW(A4),",",ROW(A26),",",ROW(A76)) -> 4,26,76 | F47: - | L47: - | M47: - | N47: - | S47: Operational, Productivity | T47: =IF(Config!$B$2='Data Validations'!$E$2,Text!B47,IF(Config!$B$2='Data Validations'!$E$3,Text!C47,"Select a lanaguage in config")) -> Allow iOS and Android devices to access on-premises resources (such as file and print services), protected by Conditional Access, MFA etc. without the need for additional VPN hardware and inbound ports | U47: Identity, End User Compute, Networking | V47: https://intune.microsoft.com/ | W47: Intune Service Administrator + Azure Contributor | X47: Scoped (on-premises install / connector Groups) | Y47: VPN/Remote Access | Z47: Network | AA47: Yes | AC47: Zero Trust: Identity | AD47: N/A - Migration to Defender for Identity Only
A48: Microsoft Entra ID - Third party SaaS Applications (SSO) | B48: M365 E3, M365 F3 | C48: Feature | D48: =CONCATENATE(ROW(A4),",",ROW(A26)) -> 4,26 | F48: - | L48: - | M48: - | N48: - | S48: Operational, Productivity | T48: =IF(Config!$B$2='Data Validations'!$E$2,Text!B48,IF(Config!$B$2='Data Validations'!$E$3,Text!C48,"Select a lanaguage in config")) -> Greatly improves the user experience with a common sign on experience, provides Conditional Access and MFA even to apps that do not support them. Greatly simplifies the Joiners/Movers/Leavers process as user effectively only have one identity, rather than and identity for each application | U48: Identity, End User Compute, Networking | V48: https://entra.microsoft.com | W48: Cloud Application Administrator | X48: Scoped (user and Groups) | Y48: Identity and Access Management | Z48: Applications | AA48: Yes | AC48: Zero Trust: Identity
A49: Global Secure Access: Microsoft Entra Private Access - Quick Access | B49: M365 E3, M365 F3, Entra Suite for non-M365 Services | C49: Feature | D49: =CONCATENATE(ROW(A4),",",ROW(A26),",",ROW(A46)) -> 4,26,46 | F49: - | L49: - | M49: - | N49: - | S49: Operational, Risk Reduction, Productivity | T49: =IF(Config!$B$2='Data Validations'!$E$2,Text!B49,IF(Config!$B$2='Data Validations'!$E$3,Text!C49,"Select a lanaguage in config")) -> With Microsoft Entra Private Access (Quick Access), organizations can define specific fully qualified domain names (FQDNs) or IP addresses of private resources to include in the traffic for Microsoft Entra Private Access. Quick Access automatically creates and configures the enterprise applications assoicated with it, which in turn can be protected by conditional access. This is directly inline with Zero Trust Networking | U49: Identity, End User Compute, Networking | V49: https://entra.microsoft.com | W49: Global Secure Access Administrator role | X49: Scoped (to CA policy) | Y49: Security Service Edge | Z49: Applications/network | AA49: Yes
A50: Global Secure Access: Microsoft Entra Private Access - Per-App | B50: M365 E3, M365 F3, Entra Suite for non-M365 Services | C50: Feature | D50: =CONCATENATE(ROW(A4),",",ROW(A26),",",ROW(A46)) -> 4,26,46 | F50: - | L50: - | M50: - | N50: - | S50: Operational, Risk Reduction, Productivity | T50: =IF(Config!$B$2='Data Validations'!$E$2,Text!B50,IF(Config!$B$2='Data Validations'!$E$3,Text!C50,"Select a lanaguage in config")) -> With Microsoft Entra Private Access (Per-App Access), organizations can define specific fully qualified domain names (FQDNs) or IP addresses of private resources to include in the traffic for Microsoft Entra Private Access. For per-app access, the enterprise application created for the app can be segmentated (upto 500 segments) to define all the specific FQDN's, IPs and ports used for that app. This may include access to the a server side front end application and the database backend. Only the app is presented to the user, protected by conditional access, rather than all on-premises services on a VPN. This is directly inline with Zero Trust Networking | U50: Identity, End User Compute, Networking | V50: https://entra.microsoft.com | W50: Global Secure Access Administrator role | X50: Scoped (to CA policy) | Y50: Security Service Edge | Z50: Applications/network | AA50: Yes
A51: Global Secure Access: Microsoft Entra Private Access - Remote Network vs Client App | B51: M365 E3, M365 F3, Entra Suite for non-M365 Services | C51: Consideration | D51: =CONCATENATE(ROW(A4),",",ROW(A26),",",ROW(A46)) -> 4,26,46 | F51: - | L51: - | M51: - | N51: - | S51: Operational, Risk Reduction, Productivity | T51: =IF(Config!$B$2='Data Validations'!$E$2,Text!B51,IF(Config!$B$2='Data Validations'!$E$3,Text!C51,"Select a lanaguage in config")) -> The connection to the Global Secure Access service can come from an organizations network or directly from client devices. The client app allows for connections from anywhere. However, if devices only connect from a physical location, such as an office, then the access can be configured directly from the router rather than each device with needing an app on each device. The per device app is required for devices that connect remotely | U51: Identity, End User Compute, Networking | V51: https://entra.microsoft.com | W51: Global Secure Access Administrator role | X51: Scoped (to CA policy) | Y51: Security Service Edge | Z51: Applications/network | AA51: Yes
A52: Global Secure Access: Microsoft Entra Private Access - Universal Tenant Restrictions | B52: Entra Suite | C52: Feature | D52: =CONCATENATE(ROW(A49)) -> 49 | F52: - | L52: - | M52: - | N52: - | S52: Operational, Risk Reduction | T52: =IF(Config!$B$2='Data Validations'!$E$2,Text!B52,IF(Config!$B$2='Data Validations'!$E$3,Text!C52,"Select a lanaguage in config")) -> Tenant restricitions v2 allows organizations to block which apps user can access when they are on the corporate network or corporate devices. This includes which Microsoft 365 tenants they can access. For example, if a user creates a personal M365 tenant, they will not be able to access that tenant from a corporate device which can prevent accidental or malicous data loss. This is especially effective as SaaS services use common URLs. | V52: https://entra.microsoft.com | W52: Security Administrator | X52: Scoped (although applies to all Users, can scope per External Application) | Y52: Security Service Edge | AA52: Yes
A53: Global Secure Access: Microsoft Entra Internet Access - Traffic Logs | B53: Entra Suite | C53: Product | D53: =CONCATENATE(ROW(A4),",",ROW(A46)) -> 4,46 | F53: - | L53: - | M53: - | N53: - | S53: Operational | T53: =IF(Config!$B$2='Data Validations'!$E$2,Text!B53,IF(Config!$B$2='Data Validations'!$E$3,Text!C53,"Select a lanaguage in config")) -> Monitoring the traffic for Global Secure Access is an important activity for ensuring your tenant is configured correctly and that your users are getting the best experience possible. The Global Secure Access traffic logs (preview) provide insight into who is accessing what resources, where they're accessing them from, and what action took place. | V53: https://entra.microsoft.com | W53: Security Administrator | X53: Scoped (although applies to all Users, can scope per user session) | Y53: Security Service Edge | AA53: Yes
A54: Global Secure Access: Microsoft Entra Internet Access - Web Category Filtering | B54: Entra Suite | C54: Product | D54: =CONCATENATE(ROW(A4),",",ROW(A46)) -> 4,46 | F54: - | L54: - | M54: - | N54: - | S54: Operational, Risk Reduction, Productivity | T54: =IF(Config!$B$2='Data Validations'!$E$2,Text!B54,IF(Config!$B$2='Data Validations'!$E$3,Text!C54,"Select a lanaguage in config")) -> Microsoft Entra Internet Access's first Secure Web Gateway (SWG) features include web content filtering based on domain names. Microsoft integrates granular filtering policies with Microsoft Entra ID and Microsoft Entra Conditional Access, which results in filtering policies that are user-aware, context-aware, and easy to manage. | V54: https://entra.microsoft.com | W54: Global Secure Access Administrator role | X54: Scoped (although applies to all Users, can scope per category) | Y54: Security Service Edge | AA54: Yes
A55: Global Secure Access: Microsoft Entra Internet Access - Fully Qualified Domain Name (FQDN) Filtering | B55: Entra Suite | C55: Product | D55: =CONCATENATE(ROW(A4),",",ROW(A46)) -> 4,46 | F55: - | L55: - | M55: - | N55: - | S55: Operational, Risk Reduction, Productivity | T55: =IF(Config!$B$2='Data Validations'!$E$2,Text!B55,IF(Config!$B$2='Data Validations'!$E$3,Text!C55,"Select a lanaguage in config")) -> nter a name, select a web category or a valid FQDN, and then select Add. Valid FQDNs in this feature can also include wildcards using the asterisk symbol, *. | V55: https://entra.microsoft.com | W55: Global Secure Access Administrator role | X55: Scoped (although applies to all Users, can scope per FQDN) | Y55: Security Service Edge | AA55: Yes
A56: Modernise JML Process | B56: _ | C56: _ | D56: _ | E56: _ | F56: _ | G56: _ | H56: _ | I56: _ | J56: _ | K56: _ | L56: _ | M56: _ | N56: _ | O56: _ | P56: _ | Q56: _ | R56: _ | S56: _ | T56: =IF(Config!$B$2='Data Validations'!$E$2,Text!B56,IF(Config!$B$2='Data Validations'!$E$3,Text!C56,"Select a lanaguage in config")) -> _ | U56: _ | V56: _ | W56: _ | X56: _ | Y56: _ | Z56: _ | AA56: _
A57: Suggestion - HR System Integration (who should be in Directory) | B57: M365 E3, M365 F3 | C57: Suggestion | D57: =CONCATENATE(ROW(A4)) -> 4 | F57: - | L57: - | M57: - | N57: - | S57: Operational | T57: =IF(Config!$B$2='Data Validations'!$E$2,Text!B57,IF(Config!$B$2='Data Validations'!$E$3,Text!C57,"Select a lanaguage in config")) -> Can help automate who should be in your Directory which can lead to automations within the Joiners/Movers/Leavers process. It also helps ensure only the right identities are in the directory and not large numbers of stale accounts. This can make lateral movement more difficult, reducing your surface area of attack. This also helps control application/services license costs and distribution of these licenses. This creates cost savings in admin work and license management | U57: Identity, Server Infrastructure | V57: https://entra.microsoft.com | W57: Cloud Application Administrator (direct AAD) | X57: Organization Specific (local directory sync) | Y57: Identity and Access Management | Z57: Identity | AA57: Yes | AB57: Zero Trust Foundations Assessment | AC57: Zero Trust: Identity | AD57: N/A
A58: Configure Entra Inbound Provisioning API | B58: M365 E3, M365 F3 | C58: Configuration | D58: =CONCATENATE(ROW(A4)) -> 4 | F58: - | L58: - | M58: - | N58: - | S58: Operational | T58: =IF(Config!$B$2='Data Validations'!$E$2,Text!B58,IF(Config!$B$2='Data Validations'!$E$3,Text!C58,"Select a lanaguage in config")) -> The inbound provisioning API helps organizations handle the issue of there not being a single version of truth of who should be in the directory. This API can take data from any source, be it a HR app, Payroll app, a spreadsheet or SQL tables. From this data, users can either be provisioned directly in Entra ID or, via a connector, directly into Active Directory to be synchronised as a hybrid user | U58: Identity, Server Infrastructure | V58: https://entra.microsoft.com | W58: Application Administrator + Hybrid Identity administrator | X58: Scoped (based on source of data) | Y58: Identity and Access Management | Z58: Identity
A59: Consideration - Access to Microsoft Identity Manager (MIM) CALs (EOL 2029) | B59: M365 E3, M365 F3 | C59: Consideration | F59: - | L59: - | M59: - | N59: - | S59: Operational | T59: =IF(Config!$B$2='Data Validations'!$E$2,Text!B59,IF(Config!$B$2='Data Validations'!$E$3,Text!C59,"Select a lanaguage in config")) -> Microsoft Identity Manager (MIM) can link together Identity Providers, such as Active Directory and Microsoft Entra ID with other identity driven services such as HR systems and applications. MIM can draw identities, attributes and information from multiple sources (into the MIM metaverse) and then apply rules and transformations and export to back to any connected system. For example, MIM can take information from a HR system and use this create users in Active Directory, assigning or updating the right attributes and group memberships through automated workflows. This can help modernise and automate the Joiners/Movers/Leavers process | U59: Identity, Server Infrastructure
A60: Process - Disable Accounts not used in last 30 days | B60: M365 E3, M365 F3 | C60: Process | E60: Good | F60: - | L60: - | M60: - | N60: - | S60: Risk Reduction, Operational | T60: =IF(Config!$B$2='Data Validations'!$E$2,Text!B60,IF(Config!$B$2='Data Validations'!$E$3,Text!C60,"Select a lanaguage in config")) -> Reduces surface area of attack by removing stale accounts that can be used for lateral movement. Stale accounts tend to be unmonitored and there is no one to "complain" their account is behaving abnormally. | U60: Identity | V60: https://entra.microsoft.com | W60: N/A (On-prem activity) | X60: Organization Specific (internal governance) | Y60: Identity and Access Management | Z60: Identity | AA60: Yes | AB60: Zero Trust Foundations Assessment | AC60: Zero Trust: Identity
A61: Self Service Group Management | B61: M365 E3, M365 F3 | C61: Feature | D61: =CONCATENATE(ROW(A4)) -> 4 | F61: - | L61: - | M61: - | N61: - | S61: Operational, Productivity | T61: =IF(Config!$B$2='Data Validations'!$E$2,Text!B61,IF(Config!$B$2='Data Validations'!$E$3,Text!C61,"Select a lanaguage in config")) -> Puts limited controls out to the organization, allowing owners of resources – and in turn the group associated with those resources – to approve access without putting the load on the helpdesk and reducing bureaucracy. However, although access can be approved or denied to add users to a group, there is no built in process to remove users from the group. This can be achieved with Microsoft Entra Identity Governance. | U61: Identity, Helpdesk | V61: https://entra.microsoft.com | W61: Privileged Role Administrator | X61: Organization Specific (Administrative Units) | Y61: Identity and Access Management | Z61: Identity | AA61: Yes | AB61: WorkshopPLUS - Microsoft Azure: Identity | AC61: Zero Trust: Identity | AD61: Microsoft Entra ID: Automation & Efficiencies
A62: Dynamic User Groups | B62: M365 E3, M365 F3 | C62: Feature | D62: =CONCATENATE(ROW(A4)) -> 4 | F62: - | L62: - | M62: - | N62: - | S62: Operational, Productivity | T62: =IF(Config!$B$2='Data Validations'!$E$2,Text!B62,IF(Config!$B$2='Data Validations'!$E$3,Text!C62,"Select a lanaguage in config")) -> Groups are defined by users attributes in Active Directory rather than static group membership. This can help automate access to resources (including removing access to older resources and gaining access to new resources) without to manually update multiple groups during a change. This can help simplify the Joiners/Movers/Leavers process | U62: Identity, End User Compute | V62: https://entra.microsoft.com | W62: Group Administrator, Intune Administrator, User Administrator | X62: Organization Specific (Administrative Units) | Y62: Identity and Access Management | Z62: Identity | AA62: Yes | AB62: WorkshopPLUS - Microsoft Azure: Identity | AC62: Zero Trust: Identity | AD62: Microsoft Entra ID: Automation & Efficiencies
A63: Microsoft Entra Identity Governance - Access Reviews | B63: M365 Defender Suite, M365 Defender Suite FLW | C63: Feature | D63: =CONCATENATE(ROW(A4),",",ROW(A9),",",ROW(A46),",",ROW(A48),",",ROW(A50)) -> 4,9,46,48,50 | E63: Better | F63: - | L63: - | M63: - | N63: - | S63: Operational, Risk Reduction, Productivity | T63: =IF(Config!$B$2='Data Validations'!$E$2,Text!B63,IF(Config!$B$2='Data Validations'!$E$3,Text!C63,"Select a lanaguage in config")) -> Access Reviews can help control permission (not privilege) creep by providing process to not only grant access but also remove it as users move through your organization. These processes can then be managed by the business rather than IT. Effectively, IT can have full control but not the day to day running of granting access to resources. This removes bottle necks to access whilst also improving auditing and accountability | U63: Identity, End User Compute, Helpdesk | V63: https://entra.microsoft.com | W63: Based on Requirement | X63: Scoped (Users and Groups) | Y63: Identity Governance | Z63: Identity/Visibility, Automation and Orchestration | AA63: Yes | AB63: WorkshopPLUS - Microsoft Azure: Identity | AC63: Zero Trust: Identity | AD63: Microsoft Entra ID: Governance
A64: Microsoft Entra Identity Governance - Entitlement Packages | B64: M365 Defender Suite, M365 Defender Suite FLW | C64: Feature | D64: =CONCATENATE(ROW(A4),",",ROW(A9),",",ROW(A46),",",ROW(A48),",",ROW(A50)) -> 4,9,46,48,50 | E64: Better | F64: - | L64: - | M64: - | N64: - | S64: Operational, Risk Reduction, Productivity | T64: =IF(Config!$B$2='Data Validations'!$E$2,Text!B64,IF(Config!$B$2='Data Validations'!$E$3,Text!C64,"Select a lanaguage in config")) -> Groups access to Microsoft Entra ID based services (groups, Teams, enterprise applications, SharePoint sites, Admin roles, Power Platform resources and M365 licensing) into Entitlement Packages. Significantly reduces bureaucracy, greatly simplifies the Joiners/Movers/Leavers process, can greatly reduce permission creep and reduce load on the helpdesk. Can be backed with Access Reviews to further improve auditing and accountability. Effectively IT can have full control over access but none of the day to day running. | U64: Identity, End User Compute, Information Governance | V64: https://entra.microsoft.com | W64: Based on Requirement | X64: Scoped (Users and Groups) | Y64: Identity Governance | Z64: Identity/Visibility, Automation and Orchestration | AA64: Yes | AB64: WorkshopPLUS - Microsoft Azure: Identity | AC64: Zero Trust: Identity
A65: Microsoft Entra Identity Governance - Lifecycle Workflows | B65: Identity Governance SKU | C65: Feature | D65: =CONCATENATE(ROW(A4),",",ROW(A9),",",ROW(A46),",",ROW(A48),",",ROW(A50)) -> 4,9,46,48,50 | F65: - | L65: - | M65: - | N65: - | S65: Operational, Risk Reduction, Productivity | T65: =IF(Config!$B$2='Data Validations'!$E$2,Text!B65,IF(Config!$B$2='Data Validations'!$E$3,Text!C65,"Select a lanaguage in config")) -> Lifecycle Workflows can add automation into the Joiners/Movers/Leavers process by adding actions that triggered by attribute changes to user objects (including creation of object). Actions can include (but not limited to) adding users to entitlement packages (trigger approval workflow), emailing managers, adding users to group or custom actions which triggers Azure Logic App(s). This allows effective automation for all users, including those who may require access to serveral business areas, all with with autonomy and accountability. | U65: Identity, End User Compute, Information Governance | V65: https://entra.microsoft.com | W65: Based on Requirement | X65: Scoped (Users and Groups) | Y65: Identity Governance | Z65: Identity/Visibility, Automation and Orchestration | AA65: Yes
A66: Microsoft Entra Identity Governance - User-to-Group Affilation Access Reviews | B66: Identity Governance SKU | C66: Feature | D66: =CONCATENATE(ROW(A63)) -> 63 | F66: - | L66: - | M66: - | N66: - | S66: Operational, Risk Reduction, Productivity | T66: =IF(Config!$B$2='Data Validations'!$E$2,Text!B66,IF(Config!$B$2='Data Validations'!$E$3,Text!C66,"Select a lanaguage in config")) -> This Machine Learning based recommendation opens the journey to automate access reviews, thereby enabling intelligent automation and reducing access rights attestation fatigue. This recommendation detects user affiliation with other users within the group, based on organization's reporting-structure similarity. The recommendation relies on a scoring mechanism, which is calculated by computing the user’s average distance with the remaining users in the group. Users who are distant from all the other group members based on their organization's chart, are considered to have "low affiliation" within the group. | U66: Identity, End User Compute, Information Governance | V66: https://entra.microsoft.com | W66: Based on Requirement | X66: Scoped (Users and Groups) | Y66: Identity Governance | Z66: Identity/Visibility, Automation and Orchestration | AA66: Yes
A67: Guest Management | B67: _ | C67: _ | D67: _ | E67: _ | F67: _ | G67: _ | H67: _ | I67: _ | J67: _ | K67: _ | L67: _ | M67: _ | N67: _ | O67: _ | P67: _ | Q67: _ | R67: _ | S67: _ | T67: =IF(Config!$B$2='Data Validations'!$E$2,Text!B67,IF(Config!$B$2='Data Validations'!$E$3,Text!C67,"Select a lanaguage in config")) -> _ | U67: _ | V67: _ | W67: _ | X67: _ | Y67: _ | Z67: _ | AA67: _
A68: External Identities (B2B 1:5 billing model) | B68: M365 E3, M365 F3 | C68: Feature | D68: =CONCATENATE(ROW(A4)) -> 4 | F68: - | L68: - | M68: - | N68: - | S68: Operational, Productivity | T68: =IF(Config!$B$2='Data Validations'!$E$2,Text!B68,IF(Config!$B$2='Data Validations'!$E$3,Text!C68,"Select a lanaguage in config")) -> B2B Guests are identities that exist in another organizations Microsoft Entra ID tenant and can be invited into your tenant. The Guest account authenticates in their own Microsoft Entra ID and can then be challenged by your organizations conditional access policies, such as the requirement for MFA. For B2B guests to benefit from your organizations security controls, you must have Microsoft Entra ID Premium P1 (M365 E3/F3) or Microsoft Entra ID Premium P2 (M365 E5 security/M365 E5) licenses. For each license in your tenant, 5 B2B guests can benefit from your premium controls (such as Conditional Access, MFA). Device health attestation (compliance device) cannot be shared from the B2B guests tenant | U68: Identity | V68: https://entra.microsoft.com | W68: Guest Inviter | X68: Scoped (Users and Groups) | Y68: Identity and Access Management | Z68: Identity | AA68: Yes
A69: External Identities (MAU billing model) | B69: Azure Subscription | C69: Product | D69: =CONCATENATE(ROW(A16),",",ROW(A26)) -> 16,26 | F69: - | L69: - | M69: - | N69: - | S69: Operational, Productivity | T69: =IF(Config!$B$2='Data Validations'!$E$2,Text!B69,IF(Config!$B$2='Data Validations'!$E$3,Text!C69,"Select a lanaguage in config")) -> External Identities simplifies management and removes confusion around licensing. An organization can simply what level of protection their external identities have (Microsoft Entra ID Premium P1 OR Microsoft Entra ID Premium P2, no mix) and then start implementing controls. The 50,000 (fifty thousand) monthly active users (MAUs) are free each month. A MAU is a unique user for that month. If that MAU signs in multiple times within a month, they will only been seen as a single MAU. There is then a flat rate cost for each MAU above 50,000 per month based on license level. External Identities can allow you organization to have strong and consistent identity controls without complexity. | U69: Identity | V69: https://entra.microsoft.com | W69: Azure Contributor | X69: Tenant Wide | Y69: Identity and Access Management | Z69: Identity | AA69: Yes
A70: Identity Governance - Connected Organizations | B70: M365 Defender Suite, M365 Defender Suite FLW | C70: Feature | D70: =CONCATENATE(ROW(A64)) -> 64 | F70: - | L70: - | M70: - | N70: - | S70: Operational, Productivity | T70: =IF(Config!$B$2='Data Validations'!$E$2,Text!B70,IF(Config!$B$2='Data Validations'!$E$3,Text!C70,"Select a lanaguage in config")) -> With Microsoft Entra ID entitlement management, you can collaborate with people outside your organization. If you frequently collaborate with users in an external Microsoft Entra ID directory or domain, you can add them as a connected organization. A connected organization is another organization that you have a relationship with. In order for the users in that organization to be able to access your resources, such as your SharePoint Online sites or apps, you'll need a representation of that organization's users in that directory. Via Microsoft Entra ID Entitlement Management, you can expose Entitlement Packages to the connected organization greatly reducing the friction of collaboration and guest management. | U70: Identity, End User Compute | V70: https://entra.microsoft.com | W70: Teams Administrator, Security Administrator | X70: Scoped (Users and Groups) | Y70: Identity and Access Management | Z70: Identity | AA70: Yes
A71: External Identities B2B Direct Connect | B71: M365 E3, M365 F3 | C71: Feature | F71: - | L71: - | M71: - | N71: - | S71: Operational, Productivity | T71: =IF(Config!$B$2='Data Validations'!$E$2,Text!B71,IF(Config!$B$2='Data Validations'!$E$3,Text!C71,"Select a lanaguage in config")) -> Microsoft Entra B2B direct connect is a feature of External Identities that lets you set up a mutual trust relationship with another Microsoft Entra ID organization for seamless collaboration. This feature currently works with Microsoft Teams shared channels. With B2B direct connect, users from both organizations can work together using their home credentials and a shared channel in Teams, without having to be added to each other’s organizations as guests. Use B2B direct connect to share resources with external Microsoft Entra ID organizations. Or use it to share resources across multiple Microsoft Entra ID tenants within your own organization. | U71: Identity, End User Compute | V71: https://entra.microsoft.com | W71: Teams Administrator, Security Administrator | X71: Scoped (Groups and Teams shared channels) | Y71: Identity and Access Management | Z71: Identity | AA71: Yes
A72: Process Suggestions | B72: _ | C72: _ | D72: _ | E72: _ | F72: _ | G72: _ | H72: _ | I72: _ | J72: _ | K72: _ | L72: _ | M72: _ | N72: _ | O72: _ | P72: _ | Q72: _ | R72: _ | S72: _ | T72: =IF(Config!$B$2='Data Validations'!$E$2,Text!B72,IF(Config!$B$2='Data Validations'!$E$3,Text!C72,"Select a lanaguage in config")) -> _ | U72: _ | V72: _ | W72: _ | X72: _ | Y72: _ | Z72: _ | AA72: _ | AB72: Architectural Service - Microsoft Entra ID: Designing a Secure Cloud Identity | AC72: Zero Trust: Identity
A73: Process - Assess Microsoft 365 Secure Score - Continuous | B73: M365 E3, M365 F3 | C73: Process | E73: Good | F73: - | L73: - | M73: - | N73: - | S73: Risk Reduction, Operational | T73: =IF(Config!$B$2='Data Validations'!$E$2,Text!B73,IF(Config!$B$2='Data Validations'!$E$3,Text!C73,"Select a lanaguage in config")) -> Proactively monitor your Microsoft 365 environment, acting upon recommendations to harden your environment and improve your security posture. Allows you to track improves to score over time and how you rate against similar organizations to yourself | U73: Security | V73: https://security.microsoft.com | W73: Based on Requirement | X73: Tenant Wide | Y73: Security Management | Z73: Visibility, Automation and Orchestration | AA73: Yes | AB73: Zero Trust Foundations Assessment | AC73: Zero Trust: Identity
A74: Endpoints (Intune) | B74: __ | C74: __ | D74: __ | E74: __ | F74: __ | G74: __ | H74: __ | I74: __ | J74: __ | K74: __ | L74: __ | M74: __ | N74: __ | O74: __ | P74: __ | Q74: __ | R74: __ | S74: __ | T74: =IF(Config!$B$2='Data Validations'!$E$2,Text!B74,IF(Config!$B$2='Data Validations'!$E$3,Text!C74,"Select a lanaguage in config")) -> __ | U74: __ | V74: __ | W74: __ | X74: __ | Y74: __ | Z74: __ | AA74: __ | AC74: Zero Trust: Endpoint
A75: Intune Plan 1 Configuration - Corporate Devices | B75: _ | C75: _ | D75: _ | E75: _ | F75: _ | G75: _ | H75: _ | I75: _ | J75: _ | K75: _ | L75: _ | M75: _ | N75: _ | O75: _ | P75: _ | Q75: _ | R75: _ | S75: _ | T75: =IF(Config!$B$2='Data Validations'!$E$2,Text!B75,IF(Config!$B$2='Data Validations'!$E$3,Text!C75,"Select a lanaguage in config")) -> _ | U75: _ | V75: _ | W75: _ | X75: _ | Y75: _ | Z75: _ | AA75: _ | AB75: Secure Endpoints with Zero Trust: Microsoft Intune | AC75: Zero Trust: Endpoint
A76: Baseline Compliance Policies | B76: M365 E3, M365 F3 | C76: Configuration | D76: =CONCATENATE(ROW(A4)) -> 4 | E76: Good | F76: - | L76: - | M76: - | N76: - | S76: Risk Reduction | T76: =IF(Config!$B$2='Data Validations'!$E$2,Text!B76,IF(Config!$B$2='Data Validations'!$E$3,Text!C76,"Select a lanaguage in config")) -> Allows you to define a minimum level of security on the endpoint (iOS, Android, MacOS and Windows). The compliance of the device (health attestation) is then used for device based conditional access - i.e., of the device is not compliant to the policy, the user will not be able to access services protected with that conditional access policy. This allows you to define and confirm trust in the device before allowing access | U76: End User Compute | V76: https://intune.microsoft.com/ | W76: Intune Administrator (Endpoint Security Administrator | X76: Organization Specific (Intune RBAC and tagging) | Y76: Device Management | Z76: Devices | AA76: Yes | AC76: Zero Trust: Endpoint | AD76: Intune MAM/MDM; Cloud Attach
A77: MDM Configuration Polices - Mobile OS (iOS, Android) | B77: M365 E3, M365 F3 | C77: Feature | D77: =CONCATENATE(ROW(A76)) -> 76 | E77: Good | F77: - | L77: - | M77: - | N77: - | S77: Operational, Risk Reduction, Productivity | T77: =IF(Config!$B$2='Data Validations'!$E$2,Text!B77,IF(Config!$B$2='Data Validations'!$E$3,Text!C77,"Select a lanaguage in config")) -> These determine the end user experience, what the endpoint device configuration looks like as well as what apps can be deployed. The MDM policies allow you to remotely configure any enrolled device to conform to your organizations configuration (such as device lock down, application deployment etc.) | U77: End User Compute, Applications | V77: https://intune.microsoft.com/ | W77: Intune Administrator | X77: Organization Specific (Intune RBAC and tagging) | Y77: Device Management | Z77: Devices | AA77: Yes | AC77: Zero Trust: Endpoint
A78: MAM Policies - Mobile OS (iOS Android) | B78: M365 E3, M365 F3 | C78: Feature | D78: =CONCATENATE(ROW(A76)) -> 76 | E78: Good | F78: - | L78: - | M78: - | N78: - | S78: Operational, Risk Reduction, Productivity | T78: =IF(Config!$B$2='Data Validations'!$E$2,Text!B78,IF(Config!$B$2='Data Validations'!$E$3,Text!C78,"Select a lanaguage in config")) -> Mobile Application Management (MAM) policies control the flow of data on a device. This can prevent your organizations data being copied out of a manged application (like Outlook or Teams) to an unmanaged application on the device (such as the note taking app or native email client). Can stop common data breaches/oversharing be them accidental or malicious | U78: End User Compute, Applications | V78: https://intune.microsoft.com/ | W78: Intune Administrator | X78: Organization Specific (Intune RBAC and tagging) | Y78: Device Management | Z78: Devices | AA78: Yes | AC78: Zero Trust: Endpoint
A79: MDM Configuration Policies - Desktop OS | B79: M365 E3, M365 F3 | C79: Feature | D79: =CONCATENATE(ROW(A76)) -> 76 | E79: Good | F79: - | L79: - | M79: - | N79: - | S79: Operational, Risk Reduction, Productivity | T79: =IF(Config!$B$2='Data Validations'!$E$2,Text!B79,IF(Config!$B$2='Data Validations'!$E$3,Text!C79,"Select a lanaguage in config")) -> These determine the end user experience, what the endpoint device configuration looks like as well as what apps can be deployed. The MDM policies allow you to remotely configure any enrolled device to conform to your organizations configuration (such as device lock down, look and feel, application deployment etc.). This is similar to what you would achieve with GPOs for a domain joined device, but being able to apply these settings even if the device is off network. This can create productivity savings (users either do not have to come to a physical location to set up and can reduce the need to VPN back on-premises. | U79: End User Compute, Applications | V79: https://intune.microsoft.com/ | W79: Intune Administrator | X79: Organization Specific (Intune RBAC and tagging) | Y79: Device Management | Z79: Devices | AA79: Yes | AC79: Zero Trust: Endpoint
A80: Microsoft Entra Domain Joined or Hybrid Domain Joined | B80: M365 E3, M365 F3 | C80: Configuration | D80: =CONCATENATE(ROW(A79)) -> 79 | F80: - | L80: - | M80: - | N80: - | S80: Operational | T80: =IF(Config!$B$2='Data Validations'!$E$2,Text!B80,IF(Config!$B$2='Data Validations'!$E$3,Text!C80,"Select a lanaguage in config")) -> organizations with existing Active Directory implementations can benefit from some of the functionality provided by Microsoft Entra ID by implementing hybrid Microsoft Entra ID joined devices. These devices are joined to your on-premises Active Directory and registered with Microsoft Entra. Hybrid Microsoft Entra joined devices require network line of sight to your on-premises domain controllers periodically. Without this connection, devices become unusable. If this requirement is a concern, consider Microsoft Entra ID joining your devices. The state of a device can be used to define to compliance of a device, either via Intune compliance polices (compliant device) or Hybrid Microsoft Entra ID Domain joined (managed by GPO's in the AD domain). | U80: End User Compute | V80: https://intune.microsoft.com/ | W80: Global Admin | X80: Scoped (onboarded devices) | Y80: Device Management | Z80: Devices
A81: Endpoint Analytics | B81: M365 E3, M365 F3 | C81: Feature | D81: =CONCATENATE(ROW(A80)) -> 80 | F81: - | L81: - | M81: - | N81: - | S81: Operational, Productivity | T81: =IF(Config!$B$2='Data Validations'!$E$2,Text!B81,IF(Config!$B$2='Data Validations'!$E$3,Text!C81,"Select a lanaguage in config")) -> Endpoint analytics is part of the Microsoft Adoption Score. These analytics give you insights for measuring how your organization is working and the quality of the experience you're delivering to your users. Endpoint analytics can help identify policies or hardware issues that may be slowing down devices and help you proactively make improvements before end-users generate a help desk ticket. | U81: End User Compute, Applications | V81: https://intune.microsoft.com/ | W81: Intune Administrator | X81: Tenant Wide | Y81: Device Management | Z81: Devices
A82: Intune Plan 1 Configuration - BYOD Devices | B82: _ | C82: _ | D82: _ | E82: _ | F82: _ | G82: _ | H82: _ | I82: _ | J82: _ | K82: _ | L82: _ | M82: _ | N82: _ | O82: _ | P82: _ | Q82: _ | R82: _ | S82: _ | T82: =IF(Config!$B$2='Data Validations'!$E$2,Text!B82,IF(Config!$B$2='Data Validations'!$E$3,Text!C82,"Select a lanaguage in config")) -> _ | U82: _ | V82: _ | W82: _ | X82: _ | Y82: _ | Z82: _ | AA82: _ | AB82: Secure Endpoints with Zero Trust: Microsoft Intune | AC82: Zero Trust: Endpoint
A83: Suggestion - Intune Categories | B83: M365 E3, M365 F3 | C83: Configuration | D83: =CONCATENATE(ROW(A4)) -> 4 | F83: - | L83: - | M83: - | N83: - | S83: Operational, Productivity | T83: =IF(Config!$B$2='Data Validations'!$E$2,Text!B83,IF(Config!$B$2='Data Validations'!$E$3,Text!C83,"Select a lanaguage in config")) -> Categories can be used to define end user experiences on enrolled BYOD devices, for example, categories can be defined as user has a PIN or User doesn’t have a PIN. Categories can be used to define dynamic device groups which then apply appropriate configuration, such as enforcing a stronger PIN to unlock the device (user has PIN) vs requiring the PIN to access managed applications (user doesn't have a PIN). This allows you to enforce your security policies without breaking the users own end user experience | U83: End User Compute | V83: https://intune.microsoft.com/ | W83: Intune Administrator | X83: Organization Specific (Intune RBAC and tagging) | Y83: Modern Management (BYOD) | Z83: Devices | AA83: Yes | AC83: Zero Trust: Endpoint
A84: MDM BYOD Policies (iOS Android) | B84: M365 E3, M365 F3 | C84: Feature | D84: =CONCATENATE(ROW(A4),",",ROW(A83)) -> 4,83 | F84: - | L84: - | M84: - | N84: - | S84: Operational, Risk Reduction, Productivity | T84: =IF(Config!$B$2='Data Validations'!$E$2,Text!B84,IF(Config!$B$2='Data Validations'!$E$3,Text!C84,"Select a lanaguage in config")) -> These determine the end user experience, what the endpoint device configuration looks like as well as what apps can be deployed. The MDM policies allow you to remotely configure any enrolled device to conform to your organizations configuration (such as device lock down, application deployment etc.). The end user experience on BYOD devices can be further defined through the use of Categories | U84: End User Compute, Applications | V84: https://intune.microsoft.com/ | W84: Intune Administrator | X84: Organization Specific (Intune RBAC and tagging) | Y84: Modern Management (BYOD) | Z84: Devices | AA84: Yes | AC84: Zero Trust: Endpoint
A85: MAM BYOD Policies (iOS Android) | B85: M365 E3, M365 F3 | C85: Feature | D85: =CONCATENATE(ROW(A4),",",ROW(A76)) -> 4,76 | F85: - | L85: - | M85: - | N85: - | S85: Operational, Risk Reduction, Productivity | T85: =IF(Config!$B$2='Data Validations'!$E$2,Text!B85,IF(Config!$B$2='Data Validations'!$E$3,Text!C85,"Select a lanaguage in config")) -> Mobile Application Management (MAM) policies control the flow of data on a device. This can prevent your organizations data being copied out of a manged application (like Outlook or Teams) to an unmanaged application on the device (such as the note taking app or native email client). These controls can be applied at the application level and without device enrollment. This means uses can effectively use BYOD without enrollment, whilst having the rich client experience, all the while maintaining data security on the device. This can remove the need for a user to have a corporate device just to access collaboration apps (Outlook, Teams, Office 365) | U85: End User Compute, Applications | V85: https://intune.microsoft.com/ | W85: Intune Administrator | X85: Organization Specific (Intune RBAC and tagging) | Y85: Modern Management (BYOD) | Z85: Devices | AA85: Yes | AC85: Zero Trust: Endpoint
A86: Process - Allow BYOD Devices | B86: M365 E3, M365 F3 | C86: Process | D86: =CONCATENATE(ROW(A30)) -> 30 | F86: - | L86: - | M86: - | N86: - | S86: Operational, Productivity | T86: =IF(Config!$B$2='Data Validations'!$E$2,Text!B86,IF(Config!$B$2='Data Validations'!$E$3,Text!C86,"Select a lanaguage in config")) -> This process is give confidence there is enough security in place to support remote devices that have not initially been in your control. | U86: End User Compute | V86: N/A | W86: N/A (Process) | X86: Organization Specific (internal governance) | Y86: Modern Management | Z86: Devices | AA86: Yes | AB86: Zero Trust Foundations Assessment | AC86: Zero Trust: Identity
A87: Intune Plan 2 Configuration | B87: _ | C87: _ | D87: _ | E87: _ | F87: _ | G87: _ | H87: _ | I87: _ | J87: _ | K87: _ | L87: _ | M87: _ | N87: _ | O87: _ | P87: _ | Q87: _ | R87: _ | S87: _ | T87: =IF(Config!$B$2='Data Validations'!$E$2,Text!B87,IF(Config!$B$2='Data Validations'!$E$3,Text!C87,"Select a lanaguage in config")) -> _ | U87: _ | V87: _ | W87: _ | X87: _ | Y87: _ | Z87: _ | AA87: _
A88: Tunnel for Mobile Application Management | B88: Microsoft Intune Plan 2, M365 E3, M365 F3 | C88: Feature | D88: =CONCATENATE(ROW(A4),",",ROW(A47)) -> 4,47 | F88: - | L88: - | M88: - | N88: - | S88: Operational, Risk Reduction, Productivity | T88: =IF(Config!$B$2='Data Validations'!$E$2,Text!B88,IF(Config!$B$2='Data Validations'!$E$3,Text!C88,"Select a lanaguage in config")) -> When you use the Microsoft Tunnel VPN Gateway, you can extend Tunnel support by adding Tunnel for Mobile Application Management (MAM). Tunnel for MAM extends the Microsoft Tunnel VPN gateway to support devices that run Android or iOS, and that aren't enrolled with Microsoft Intune. With this solution, your users can use a single device that hasn't enrolled with Intune to gain secure access to the organizations on-premises apps and resources using modern authentication, Single Sign On and conditional access. With Tunnel for MAM, your users can use their own device (BYOD) for both work and personal use, without having to grant the organization’s IT department control over that device. | U88: End User Compute | V88: https://intune.microsoft.com/ | W88: Intune Administrator | X88: Organization Specific (Intune RBAC and tagging) | Y88: Modern Management (BYOD) | Z88: Devices | AA88: Yes | AC88: Zero Trust: Endpoint
A89: Management of Specialty Devices | B89: Microsoft Intune Plan 2, M365 E3, M365 F3 | C89: Feature | D89: =CONCATENATE(ROW(A76)) -> 76 | F89: - | L89: - | M89: - | N89: - | S89: Operational, Risk Reduction, Productivity | T89: =IF(Config!$B$2='Data Validations'!$E$2,Text!B89,IF(Config!$B$2='Data Validations'!$E$3,Text!C89,"Select a lanaguage in config")) -> Extends Intune device management to specialty devices, such as Smart Screens over 30", AR/VR headsets, Wearable headsets and Conference Room meeting devices. This also excludes all devices manageable with Microsoft Intune Plan 1 | U89: End User Compute | V89: https://intune.microsoft.com/ | W89: Intune Administrator | X89: Organization Specific (Intune RBAC and tagging) | Y89: Device Management | Z89: Devices | AA89: Yes | AC89: Zero Trust: Endpoint
A90: Firmware-over-the-air (FOTA) updates | B90: Microsoft Intune Plan 2, M365 E3, M365 F3 | C90: Feature | D90: =CONCATENATE(ROW(A78)) -> 78 | F90: - | L90: - | M90: - | N90: - | S90: Operational, Productivity | T90: =IF(Config!$B$2='Data Validations'!$E$2,Text!B90,IF(Config!$B$2='Data Validations'!$E$3,Text!C90,"Select a lanaguage in config")) -> Firmware Over-the-Air (FOTA) updates allow remotely updating the firmware of devices using a wireless connection, rather than requiring the devices to be physically connected to a computer or network. | U90: End User Compute, Applications | V90: https://intune.microsoft.com/ | W90: Intune Administrator | X90: Scoped (onboarded devices) | Y90: Device Management | Z90: Devices | AC90: Zero Trust: Endpoint
A91: Advanced Endpoint Management Capabilities | B91: _ | C91: _ | D91: _ | E91: _ | F91: _ | G91: _ | H91: _ | I91: _ | J91: _ | K91: _ | L91: _ | M91: _ | N91: _ | O91: _ | P91: _ | Q91: _ | R91: _ | S91: _ | T91: =IF(Config!$B$2='Data Validations'!$E$2,Text!B91,IF(Config!$B$2='Data Validations'!$E$3,Text!C91,"Select a lanaguage in config")) -> _ | U91: _ | V91: _ | W91: _ | X91: _ | Y91: _ | Z91: _ | AA91: _
A92: Remote Help | B92: M365 E3, M365 F3 | C92: Product | D92: =CONCATENATE(ROW(A79)) -> 79 | F92: - | L92: - | M92: - | N92: - | S92: Operational, Productivity | T92: =IF(Config!$B$2='Data Validations'!$E$2,Text!B92,IF(Config!$B$2='Data Validations'!$E$3,Text!C92,"Select a lanaguage in config")) -> Remote help allows helpdesk and support admins to remotely control a Windows desktop with centralised controls via Microsoft Endpoint Manager | U92: End User Compute, Helpdesk | V92: https://intune.microsoft.com/ | W92: Intune Administrator (can define custom role) | X92: Organization Specific (Intune RBAC and tagging) | Y92: Remote Access/Helpdesk | Z92: Devices | AA92: Yes | AC92: Zero Trust: Endpoint
A93: Endpoint Privilege Management | B93: M365 E5 | C93: Product | D93: =CONCATENATE(ROW(A79)) -> 79 | F93: - | L93: - | M93: - | N93: - | S93: Operational, Risk Reduction, Productivity | T93: =IF(Config!$B$2='Data Validations'!$E$2,Text!B93,IF(Config!$B$2='Data Validations'!$E$3,Text!C93,"Select a lanaguage in config")) -> Historically, IT admins have been forced to make a binary choice: run employees as standard users or local admins. If IT admins choose to run all employees as local administrators, the enterprise is left vulnerable to malicious actors. If admins choose a more conservative path and run everyone as a standard user, it comes at a cost, mostly shouldered by users and help desk staff, in the form of expensive support incidents due to restricted access to necessary work. Endpoint Privilege Management offers a better, more controlled way to manage standard users. The feature enables admins to set policies that allow standard users to perform tasks usually reserved for an administrator. Elevated privileges are offered for a discrete task, keeping the scope and time to a minimum, per organizational policies. This allows enterprises to stay secure while improving efficiency for IT teams and removing friction to accomplish work and achieve business goals. | U93: End User Compute, Helpdesk | V93: https://intune.microsoft.com/ | W93: Intune Administrator | X93: Organization Specific (device tagging) | Y93: Device Management | Z93: Devices | AC93: Zero Trust: Endpoint
A94: Advanced Endpoint Analytics | B94: M365 E3, M365 F3 | C94: Product | D94: =CONCATENATE(ROW(A81)) -> 81 | F94: - | L94: - | M94: - | N94: - | S94: Operational, Productivity | T94: =IF(Config!$B$2='Data Validations'!$E$2,Text!B94,IF(Config!$B$2='Data Validations'!$E$3,Text!C94,"Select a lanaguage in config")) -> Advanced Endpoint analytics includes additional features, including: Custom device scopes allow you to use Scope tags to slice Endpoint analytics reports to a subset of devices. You can see scores, insights, and recommendations specific to subsets of your enrolled devices, such as devices you're responsible to manage, or devices belonging to a particular business group or assigned to a specific geographic region. Anomalies monitors the health of devices in your organization for user experience and productivity regressions following configuration changes. For more information, see Anomaly detection. Also, An enhanced device timeline includes more events and lower data latency to assist with troubleshooting device issues. | U94: End User Compute, Helpdesk | V94: https://intune.microsoft.com/ | W94: Intune Administrator | X94: Organization Specific (device tagging) | Y94: Device Management | Z94: Devices | AC94: Zero Trust: Endpoint
A95: Enterprise Application Management | B95: M365 E5 | C95: Product | D95: =CONCATENATE(ROW(A76)) -> 76 | F95: - | L95: - | M95: - | N95: - | S95: Operational, Risk Reduction, Productivity | T95: =IF(Config!$B$2='Data Validations'!$E$2,Text!B95,IF(Config!$B$2='Data Validations'!$E$3,Text!C95,"Select a lanaguage in config")) -> Enables easy app discovery, deployment, and updating using a securely hosted app catalog of prepackaged apps. | U95: End User Compute, Applications | V95: https://intune.microsoft.com/ | W95: Intune Administrator | X95: Organization Specific (device tagging) | Y95: Device Management | Z95: Devices | AC95: Zero Trust: Endpoint
A96: Microsoft Cloud PKI | B96: M365 E5 | C96: Product | D96: =CONCATENATE(ROW(A76)) -> 76 | F96: - | L96: - | M96: - | N96: - | S96: Risk Reduction, Operational | T96: =IF(Config!$B$2='Data Validations'!$E$2,Text!B96,IF(Config!$B$2='Data Validations'!$E$3,Text!C96,"Select a lanaguage in config")) -> Streamline certificate lifecycle management: Manage certificates where you manage your endpoints. | U96: End User Compute, Security | V96: https://intune.microsoft.com/ | W96: Intune Administrator (can define custom role) | X96: Organization Specific (onboarded apps) | Y96: Device Management | Z96: Devices | AC96: Zero Trust: Endpoint
A97: Intune - Co Management with ConfigMgr | B97: _ | C97: _ | D97: _ | E97: _ | F97: _ | G97: _ | H97: _ | I97: _ | J97: _ | K97: _ | L97: _ | M97: _ | N97: _ | O97: _ | P97: _ | Q97: _ | R97: _ | S97: _ | T97: =IF(Config!$B$2='Data Validations'!$E$2,Text!B97,IF(Config!$B$2='Data Validations'!$E$3,Text!C97,"Select a lanaguage in config")) -> _ | U97: _ | V97: _ | W97: _ | X97: _ | Y97: _ | Z97: _ | AA97: _ | AB97: Zero Trust Foundations Assessment | AC97: Zero Trust: Endpoint
A98: ConfigMgr Update to current branch | B98: M365 E3, M365 F3 | C98: Configuration | F98: - | L98: - | M98: - | N98: - | S98: Operational | T98: =IF(Config!$B$2='Data Validations'!$E$2,Text!B98,IF(Config!$B$2='Data Validations'!$E$3,Text!C98,"Select a lanaguage in config")) -> Upgrading to latest builds of ConfigMgr not only provides the latest functionality and compatibility but also open ups the option of co-management | U98: End User Compute, Server Infrastructure | V98: On-premises configuration | W98: ConfigMgr Admin (On-prem) | X98: Organization Specific (on-premises deployment) | Y98: Device Management | Z98: Devices/Infrastructure | AA98: Yes | AC98: Zero Trust: Endpoint
A99: ConfigMgr Cloud Management Gateway | B99: M365 E3, M365 F3 | C99: Feature | D99: =CONCATENATE(ROW(A79)) -> 79 | F99: - | L99: - | M99: - | N99: - | S99: Operational | T99: =IF(Config!$B$2='Data Validations'!$E$2,Text!B99,IF(Config!$B$2='Data Validations'!$E$3,Text!C99,"Select a lanaguage in config")) -> A Cloud management gateway is effectively a cloud based distribution point allowing ConfigMgr managed devices to receive configuration, apps and updates without the need to VPN into your on-premises environment. This can reduce your surface area of attack whilst allowing for management of devices off network | U99: End User Compute, Server Infrastructure | V99: https://portal.azure.com | W99: Azure Subscription Manager + Global Admin | X99: Organization Specific (on-premises deployment) | Y99: Modern Management | Z99: Devices/Infrastructure | AA99: Yes | AC99: Zero Trust: Endpoint
A100: Co-Management Configuration | B100: M365 E3, M365 F3 | C100: Configuration | D100: =CONCATENATE(ROW(A76),",",ROW(A98)) -> 76,98 | F100: - | L100: - | M100: - | N100: - | S100: Operational, Productivity | T100: =IF(Config!$B$2='Data Validations'!$E$2,Text!B100,IF(Config!$B$2='Data Validations'!$E$3,Text!C100,"Select a lanaguage in config")) -> Co-management effectively splits what tasks can be managed via the cloud and what can be managed on-premises. This allows an organization to get the best of both worlds and eases the transition to modern management | U100: End User Compute, Server Infrastructure | V100: On-premises configuration | W100: ConfigMgr Admin (On-prem) | X100: Organization Specific (on-premises deployment) | Y100: Modern Management | Z100: Devices | AA100: Yes | AC100: Zero Trust: Endpoint
...

Sheet Text
A1: Task Name | B1: Business Justification - EN-GB | C1: Business Justification - EN-US
A2: High Level Prerequisites | B2: __ | C2: __
A3: Identity object remediation | B3: Allows for synchronisation of on-premises Active Directory accounts into Microsoft Entra ID | C3: Allows for synchronisation of on-premises Active Directory accounts into Microsoft Entra ID
A4: Microsoft Entra Connect Deployment (directory synchronisation) | B4: Creates a relationship between on-premises AD Accounts and AD accounts to make them appear as one account (single identity, effectively a hybrid identity) | C4: Creates a relationship between on-premises AD Accounts and AD accounts to make them appear as one account (single identity, effectively a hybrid identity)
A5: Recommended - Configure Password Hash Synchronisation | B5: Allows for seamless single sign on whilst also removing the need for AD FS servers. This also means no reliance on any servers for authentication on-premises reducing surface area of attack | C5: Allows for seamless single sign on whilst also removing the need for AD FS servers. This also means no reliance on any servers for authentication on-premises reducing surface area of attack
A6: Microsoft Apps for Enterprise (Office ProPlus) | B6: Always latest and greatest version of Office deployed using the modern Click to Run method. | C6: Always latest and greatest version of Office deployed using the modern Click to Run method.
A7: Data Migration | B7: _ | C7: _
A8: Exchange migration | B8: Significantly reduce or remove on-premises Exchange servers and all it's associated requirements leaving uses with an always up to date Exchange, access from anywhere, significantly larger mailboxes, transport rules and advanced compliance features on top of other benefits | C8: Significantly reduce or remove on-premises Exchange servers and all it's associated requirements leaving uses with an always up to date Exchange, access from anywhere, significantly larger mailboxes, transport rules and advanced compliance features on top of other benefits
A9: SharePoint Migration | B9: Migrate from legacy file shares to modern document management with SharePoint Online, providing an EDRM system, structured data, better searching, larger storage capacity, better insights, secure access from anywhere and access to advanced compliance features on top of other benefits | C9: Migrate from legacy file shares to modern document management with SharePoint Online, providing an EDRM system, structured data, better searching, larger storage capacity, better insights, secure access from anywhere and access to advanced compliance features on top of other benefits
A10: OneDrive Migration | B10: Migrate from legacy home drives to modern document management with OneDrive for Business, providing an EDRM system, structured data, better searching, unlimited storage capacity, secure access from anywhere and access to advanced compliance features on top of other benefits | C10: Migrate from legacy home drives to modern document management with OneDrive for Business, providing an EDRM system, structured data, better searching, unlimited storage capacity, secure access from anywhere and access to advanced compliance features on top of other benefits
A11: Identity (Microsoft Entra) | B11: __ | C11: __
A12: Strong Authentication | B12: _ | C12: _
... A197: Set Organisation Level External Sharing settings | B197: The Organisational External Sharing settings allows organisations to control their guest (external) access to SharePoint and OneDrive, in turn controlling guest management. Although the setting is at the organisation level, individual settings can still be configured on individual sites granting finite controls over more sensitive data. The "Existing Guests" only setting allows for greater governance but more admin overhead. The "New and Existing Guests" can reduce admin overheads but still allow for admin driven controls via groups of guests. | C197: The organizational External Sharing settings allows organizations to control their guest (external) access to SharePoint and OneDrive, in turn controlling guest management. Although the setting is at the organization level, individual settings can still be configured on individual sites granting finite controls over more sensitive data. The "Existing Guests" only setting allows for greater governance but more admin overhead. The "New and Existing Guests" can reduce admin overheads but still allow for admin driven controls via groups of guests.
A198: Microsoft Defender for Cloud Apps (Data Governance)
A199: Microsoft Purview Data Loss Prevention | B199: Organisations have sensitive information under their control such as financial data, intellectual property, health records, or other PII data. To help protect this sensitive data and reduce risk, they need a way to prevent their users from inappropriately sharing it with people who shouldn't have it. This practice is called data loss prevention (DLP). Microsoft Purview Data Loss Prevention can protect data in SharePoint Online (including OneDrive) and Exchange Online. It can also be used with on-premises data flowing through Office 365 via metadata from sensitivity labels. | C199: organizations have sensitive information under their control such as financial data, intellectual property, health records, or other PII data. To help protect this sensitive data and reduce risk, they need a way to prevent their users from inappropriately sharing it with people who shouldn't have it. This practice is called data loss prevention (DLP). Microsoft Purview Data Loss Prevention can protect data in SharePoint Online (including OneDrive) and Exchange Online. It can also be used with on-premises data flowing through Office 365 via metadata from sensitivity labels.
A200: Prevent Accidential Oversharing in Outlook | B200: Force a pop up in Outlook when a user attempts to share sensitive data in a way that matches the respective DLP control, which user can optionally override with justiifcation. This forces the user to check recipients before sending. Suggesting using catch all conditons and the "NOT" condition for exclusions (i.e., no pop up when sending to trusted partners) | C200: Force a pop up in Outlook when a user attempts to share sensitive data in a way that matches the respective DLP control, which user can optionally override with justiifcation. This forces the user to check recipients before sending. Suggesting using catch all conditons and the "NOT" condition for exclusions (i.e., no pop up when sending to trusted partners)
A201: Microsoft Purview Message Encryption | B201: Microsoft Purview Message Encryption (MPME, formally OME) can be used to send individually protected emails that only the intended recipients can view or action. Emails that organisations have protected with MPME effectively remain under that organisations control, even if it is in an external recipients mailbox. Encryption is certificate driven, managed by the Azure Rights Management Service, and these certificates can not only be time bound, but they can also be revoked removing access to delivered mail. Additionally Exchange transport rules, mail can be to automatically encrypt mail outbound and decrypt it inbound to work effectively and securely with Line of Business applications that send email. | C201: Microsoft Purview Message Encryption (MPME, formally OME) can be used to send individually protected emails that only the intended recipients can view or action. Emails that organizations have protected with MPME effectively remain under that organizations control, even if it is in an external recipients mailbox. Encryption is certificate driven, managed by the Azure Rights Management Service, and these certificates can not only be time bound, but they can also be revoked removing access to delivered mail. Additionally Exchange transport rules, mail can be to automatically encrypt mail outbound and decrypt it inbound to work effectively and securely with Line of Business applications that send email.
A202: Apply branding to message encryption | B202: Apply branding to messages forces the linked experince rather than the inline experience for recipients. Not only does this create a common user experince, but most importantly linked messages can be revoked by the sender and the sending organisations admins | C202: Apply branding to messages forces the linked experince rather than the inline experience for recipients. Not only does this create a common user experince, but most importantly linked messages can be revoked by the sender and the sending organizations admins
A203: Teams Data Loss Prevention | B203: Teams Data Loss Prevention extends Microsoft Purview Data Loss Prevention to Teams chat and channels. As an example, you can apply controls when someone attempts to share sensitive information in a Teams chat or channel with guests (external users). If you have a DLP policy defined to prevent this, messages with sensitive information that are sent to external users are deleted. This happens automatically, and within seconds, according to how your DLP policy is configured. | C203: Teams Data Loss Prevention extends Microsoft Purview Data Loss Prevention to Teams chat and channels. As an example, you can apply controls when someone attempts to share sensitive information in a Teams chat or channel with guests (external users). If you have a DLP policy defined to prevent this, messages with sensitive information that are sent to external users are deleted. This happens automatically, and within seconds, according to how your DLP policy is configured.
A204: Endpoint Data Loss Prevention | B204: Endpoint data loss prevention (Endpoint DLP) extends the activity monitoring and protection capabilities of Microsoft Purview DLP to sensitive items that are physically stored on Windows 10, Windows 11, and macOS (three latest released versions) devices. Once devices are onboarded into the Microsoft Purview solutions - or via Microsoft Defender for Endpoints Plan 2. Once a device is onboarded, Endpoint DLP will detect when sensitive items are used and shared. Activities include copying sensitive data to the clipboard, copying data to unmanaged storage such as USB devices or Bluetooth devices, or to unsanctioned applications, both on the device and in the cloud. This gives you the visibility and control you need to ensure that they are used and protected properly, and to help prevent risky behaviour that might compromise them. | C204: Endpoint data loss prevention (Endpoint DLP) extends the activity monitoring and protection capabilities of Microsoft Purview DLP to sensitive items that are physically stored on Windows 10, Windows 11, and macOS (three latest released versions) devices. Once devices are onboarded into the Microsoft Purview solutions - or via Microsoft Defender for Endpoints Plan 2. Once a device is onboarded, Endpoint DLP will detect when sensitive items are used and shared. Activities include copying sensitive data to the clipboard, copying data to unmanaged storage such as USB devices or Bluetooth devices, or to unsanctioned applications, both on the device and in the cloud. This gives you the visibility and control you need to ensure that they are used and protected properly, and to help prevent risky behaviour that might compromise them.
A205: On-premises Data Loss Prevention | B205: The DLP on-premises scanner relies on a full implementation of the Azure Information Protection (AIP) scanner to monitor, label and protect sensitive items. The DLP on-premises scanner crawls on-premises data-at-rest in file shares and SharePoint document libraries and folders for sensitive items that, if leaked, would pose a risk to an organisation or pose a risk of compliance policy violation. This gives them the visibility and control you need to ensure that sensitive items are used and protected properly, and to help prevent risky behaviour that might compromise them. The DLP on-premises scanner detects sensitive information by using built-in or custom sensitive information types, sensitivity labels or file properties. The information about what users are doing with sensitive items is made visible in activity explorer and you can enforce protective actions on those items via DLP policies. | C205: The DLP on-premises scanner relies on a full implementation of the Azure Information Protection (AIP) scanner to monitor, label and protect sensitive items. The DLP on-premises scanner crawls on-premises data-at-rest in file shares and SharePoint document libraries and folders for sensitive items that, if leaked, would pose a risk to an organization or pose a risk of compliance policy violation. This gives them the visibility and control you need to ensure that sensitive items are used and protected properly, and to help prevent risky behaviour that might compromise them. The DLP on-premises scanner detects sensitive information by using built-in or custom sensitive information types, sensitivity labels or file properties. The information about what users are doing with sensitive items is made visible in activity explorer and you can enforce protective actions on those items via DLP policies.
A206: Microsoft Purview Insider Risk Management | B206: Employees now have more access to create, manage, and share data across a broad spectrum of platforms and services. In most cases, organisations have limited resources and tools to identify and mitigate organisation-wide risks while also meeting compliance requirements and employee privacy standards. These risks include potential data theft by departing employees and risk of data leaks of information outside your organisation by accidental oversharing or malicious intent. Microsoft Purview Insider Risk Management uses the full breadth of service and 3rd-party indicators (such as feeds from HR systems) to help you quickly identify, triage, and act on potentially risky activity. By using logs from Microsoft 365 and Microsoft Graph, Insider Risk Management allows you to define specific policies to identify risk indicators. After identifying the risks, you can take action to mitigate these risks, and if necessary open investigation cases and take appropriate action, be that an IT driven data breach investigation or HR/Legal action. | C206: Employees now have more access to create, manage, and share data across a broad spectrum of platforms and services. In most cases, organizations have limited resources and tools to identify and mitigate organization-wide risks while also meeting compliance requirements and employee privacy standards. These risks include potential data theft by departing employees and risk of data leaks of information outside your organization by accidental oversharing or malicious intent. Microsoft Purview Insider Risk Management uses the full breadth of service and 3rd-party indicators (such as feeds from HR systems) to help you quickly identify, triage, and act on potentially risky activity. By using logs from Microsoft 365 and Microsoft Graph, Insider Risk Management allows you to define specific policies to identify risk indicators. After identifying the risks, you can take action to mitigate these risks, and if necessary open investigation cases and take appropriate action, be that an IT driven data breach investigation or HR/Legal action.
A207: (Preview) Enable Adaptive DLP controls | B207: Prevent users for taking actions, either malicously or accidentally which could be considered as risky - such as downloading a volume of content or sharing excessively. Adaptive DLP controls apply on the users risk score from Insider Risk Management. Appropriate controls can be applied based risk levels, such as policy tips only for low level risk, overrides required for medium level and block at high risk. | C207: Prevent users for taking actions, either malicously or accidentally which could be considered as risky - such as downloading a volume of content or sharing excessively. Adaptive DLP controls apply on the users risk score from Insider Risk Management. Appropriate controls can be applied based risk levels, such as policy tips only for low level risk, overrides required for medium level and block at high risk.
A208: Data Security Posture Management (DSPM) | B208: Use Data Security Posture Management (DSPM) to quickly identify unprotected sensitive data assets and potentially risky user activities in your organisation. | C208: Use Data Security Posture Management (DSPM) to quickly identify unprotected sensitive data assets and potentially risky user activities in your organization.
A209: Data Lifecycle Management | B209: _ | C209: _
A210: Microsoft Purview Data Mapping | B210: The Microsoft Purview data map provides the foundation for data discovery and data governance. It captures metadata about data present in analytics, software-as-a-service (SaaS), and operation systems in hybrid, on-premises, and multi-cloud environments. The Microsoft Purview Data Map stays up to date with its built-in scanning and classification system. All Microsoft Purview accounts have a data map that elastically grow starting at one capacity unit (1 CU = 10GB of meta data and up to 25 operations/sec). They scale up and down based on request load and metadata stored within the data map. Microsoft Purview Data Map can also track data lineage (Data lineage is broadly understood as the lifecycle that spans the data’s origin, and where it moves over time across the data estate) and Data Classification (Data classification in the Microsoft Purview governance portal is a way of categorizing data assets by assigning unique logical tags or classes to the data assets. Classification is based on the business context of the data). | C210: The Microsoft Purview data map provides the foundation for data discovery and data governance. It captures metadata about data present in analytics, software-as-a-service (SaaS), and operation systems in hybrid, on-premises, and multi-cloud environments. The Microsoft Purview Data Map stays up to date with its built-in scanning and classification system. All Microsoft Purview accounts have a data map that elastically grow starting at one capacity unit (1 CU = 10GB of meta data and up to 25 operations/sec). They scale up and down based on request load and metadata stored within the data map. Microsoft Purview Data Map can also track data lineage (Data lineage is broadly understood as the lifecycle that spans the data’s origin, and where it moves over time across the data estate) and Data Classification (Data classification in the Microsoft Purview governance portal is a way of categorizing data assets by assigning unique logical tags or classes to the data assets. Classification is based on the business context of the data).
... A223: Copilot Usage & Risk Analytics | B223: Provides unified visibility into Copilot and AI agent usage across the organisation, enabling monitoring of adoption, identification of risk patterns, and detection of anomalous or potentially unsafe behaviors. Supports governance, compliance reporting, and continuous improvement of AI deployment strategies. | C223: Provides unified visibility into Copilot and AI agent usage across the organization, enabling monitoring of adoption, identification of risk patterns, and detection of anomalous or potentially unsafe behaviors. Supports governance, compliance reporting, and continuous improvement of AI deployment strategies.
A224: AI Governance & Security (Copilots, Agents, GenAI) | B224: _
A225: Microsoft Purview DSPM for AI | B225: Provides visibility into how AI tools and Copilots interact with sensitive data, reducing oversharing and privacy risk while allowing AI adoption to proceed with clear, enforceable data guardrails. | C225: Provides visibility into how AI tools and Copilots interact with sensitive data, reducing oversharing and privacy risk while allowing AI adoption to proceed with clear, enforceable data guardrails.
A226: Copilot Control System | B226: Creates a unified governance layer for Copilot and AI agents, ensuring data access, compliance, and audit controls scale consistently as AI usage expands across the organisation. | C226: Creates a unified governance layer for Copilot and AI agents, ensuring data access, compliance, and audit controls scale consistently as AI usage expands across the organization.
A227: Defender for Cloud Apps (GenAI discovery) | B227: Reveals and controls generative AI usage across sanctioned and unsanctioned tools, reducing blind spots and preventing data exposure through unmanaged or high‑risk AI services. | C227: Reveals and controls generative AI usage across sanctioned and unsanctioned tools, reducing blind spots and preventing data exposure through unmanaged or high‑risk AI services.
A228: Security Copilot (as a governed operator, not a detector) | B228: Improves security and compliance operations by accelerating investigation, triage, and reporting, enabling teams to respond faster and more effectively without increasing staffing or complexity. | C228: Improves security and compliance operations by accelerating investigation, triage, and reporting, enabling teams to respond faster and more effectively without increasing staffing or complexity.
A229: Agent governance (Copilot Studio / Foundry) | B229: Ensures custom AI agents are developed, deployed, and operated within approved data, security, and lifecycle boundaries, preventing unsafe automation and inconsistent agent behaviour. | C229: Ensures custom AI agents are developed, deployed, and operated within approved data, security, and lifecycle boundaries, preventing unsafe automation and inconsistent agent behavior.
A230: Agent Identity, Lifecycle & Runtime Governance (Agent 365) | B230: Introduces centralised identity, ownership, and runtime governance for AI agents, enabling organisations to manage autonomous agents with the same visibility, accountability, and control as human users. | C230: Introduces centralized identity, ownership, and runtime governance for AI agents, enabling organizations to manage autonomous agents with the same visibility, accountability, and control as human users.
A231: AI Risk Posture Management (Cross-Platform) | B231: Aggregates data security, agent activity, and AI usage into a unified risk and control model across the enterprise. Builds on capabilities such as Purview DSPM for AI, Defender for Cloud Apps, and Copilot governance to deliver unified AI risk visibility and control. | C231: Aggregates data security, agent activity, and AI usage into a unified risk and control model across the enterprise. Builds on capabilities such as Purview DSPM for AI, Defender for Cloud Apps, and Copilot governance to deliver unified AI risk visibility and control.
A232: AI Data Exposure Controls (Real-Time) | B232: Extends data protection controls into real-time AI interactions, ensuring sensitive data is governed not only at rest or in transit, but dynamically during Copilot and agent-driven workflows. Prevents oversharing, unauthorised exposure, and misuse of sensitive information by enforcing policy-driven controls at the point of AI interaction. | C232: Extends data protection controls into real-time AI interactions, ensuring sensitive data is governed not only at rest or in transit, but dynamically during Copilot and agent-driven workflows. Prevents oversharing, unauthorized exposure, and misuse of sensitive information by enforcing policy-driven controls at the point of AI interaction.
A233: Governance Policy (Business and Regulatory) | B233: _ | C233: _
A234: Microsoft Purview Compliance Manager | B234: Microsoft Purview Compliance Manager is a feature in the Microsoft Purview compliance portal that helps organisations manage multicloud compliance requirements with greater ease and convenience. Compliance Manager can help throughout the compliance journey, from taking inventory of data protection risks to managing the complexities of implementing controls, staying current with regulations and certifications, and reporting to auditors. Compliance Manager helps simplify compliance and reduce risk by providing: Pre-built assessments for common industry and regional standards and regulations, or custom assessments to meet your unique compliance needs; Workflow capabilities to help efficiently complete risk assessments through a single tool; Detailed step-by-step guidance on suggested improvement actions to help organisations comply with the standards and regulations that are most relevant for them. For actions that are managed by Microsoft, implementation details and audit results are displayed. A risk-based compliance score to help understand compliance posture by measuring progress in completing improvement actions. | C234: Microsoft Purview Compliance Manager is a feature in the Microsoft Purview compliance portal that helps organizations manage multicloud compliance requirements with greater ease and convenience. Compliance Manager can help throughout the compliance journey, from taking inventory of data protection risks to managing the complexities of implementing controls, staying current with regulations and certifications, and reporting to auditors. Compliance Manager helps simplify compliance and reduce risk by providing: Pre-built assessments for common industry and regional standards and regulations, or custom assessments to meet your unique compliance needs; Workflow capabilities to help efficiently complete risk assessments through a single tool; Detailed step-by-step guidance on suggested improvement actions to help organizations comply with the standards and regulations that are most relevant for them. For actions that are managed by Microsoft, implementation details and audit results are displayed. A risk-based compliance score to help understand compliance posture by measuring progress in completing improvement actions.
A235: Microsoft Purview Communication Compliance | B235: Protecting sensitive information and detecting and acting on workplace harassment incidents is an important part of compliance with internal policies and standards. Microsoft Purview Communication Compliance helps minimize these risks by helping quickly detect, capture, and take remediation actions for email and Microsoft Teams communications. These include potentially inappropriate communications containing profanity, threats, and harassment and communications that share sensitive information inside and outside of an organisation. Microsoft Purview Communication Compliance takes advantage of Trainable classifiers to detect policy violations. It must be stressed that communications compliance will only search for what it is configured to do so, i.e., what an organisation has defined in scoped Communication Compliance policies. | C235: Protecting sensitive information and detecting and acting on workplace harassment incidents is an important part of compliance with internal policies and standards. Microsoft Purview Communication Compliance helps minimize these risks by helping quickly detect, capture, and take remediation actions for email and Microsoft Teams communications. These include potentially inappropriate communications containing profanity, threats, and harassment and communications that share sensitive information inside and outside of an organization. Microsoft Purview Communication Compliance takes advantage of Trainable classifiers to detect policy violations. It must be stressed that communications compliance will only search for what it is configured to do so, i.e., what an organization has defined in scoped Communication Compliance policies.
A236: Microsoft Priva Risk Management | B236: Privacy is top of mind for most organisations, and concerns about how private data is handled are steadily increasing. Regulations and laws such as the EU's General Data Protection Regulation (GDPR) and the California Consumer Privacy Act (CCPA) impact people around the world, setting rules for how organisations store personal data and giving people rights to manage personal data collected by an organisation. To meet regulatory requirements and build customer trust, organisations need to take a "privacy by default" stance. Rather than manual processes and a patchwork of tools, organisations need a comprehensive solution to address common challenges such as: Protecting the increasing amounts of unstructured data from privacy issues arising from human error; Helping employees adopt sound data handling practices and training them to spot and fix issues; Understanding the potential risks in the amount and type of personal data they store and share and Fulfilling data subject requests, or subject rights requests, efficiently and on-time. Microsoft Priva helps meet these challenges so an organisation can achieve their privacy goals. | C236: Privacy is top of mind for most organizations, and concerns about how private data is handled are steadily increasing. Regulations and laws such as the EU's General Data Protection Regulation (GDPR) and the California Consumer Privacy Act (CCPA) impact people around the world, setting rules for how organizations store personal data and giving people rights to manage personal data collected by an organization. To meet regulatory requirements and build customer trust, organizations need to take a "privacy by default" stance. Rather than manual processes and a patchwork of tools, organizations need a comprehensive solution to address common challenges such as: Protecting the increasing amounts of unstructured data from privacy issues arising from human error; Helping employees adopt sound data handling practices and training them to spot and fix issues; Understanding the potential risks in the amount and type of personal data they store and share and Fulfilling data subject requests, or subject rights requests, efficiently and on-time. Microsoft Priva helps meet these challenges so an organization can achieve their privacy goals.
... A241: Microsoft Purview Information Barriers | B241: Microsoft 365 enables communication and collaboration across groups and organisations and supports ways to restrict communication and collaboration among specific groups of users when necessary. This may include situations or scenarios where you want to restrict communication and collaboration between two groups to avoid a conflict of interest from occurring in your organisation. This may also include situations when you need to restrict communication and collaboration between certain people inside organisations to safeguard internal information. Microsoft Purview Information Barriers (IB) is supported in Microsoft Teams, SharePoint Online, and OneDrive for Business. A compliance administrator or IB administrator can define policies to allow or prevent communications between groups of users in Microsoft Teams. | C241: Microsoft 365 enables communication and collaboration across groups and organizations and supports ways to restrict communication and collaboration among specific groups of users when necessary. This may include situations or scenarios where you want to restrict communication and collaboration between two groups to avoid a conflict of interest from occurring in your organization. This may also include situations when you need to restrict communication and collaboration between certain people inside organizations to safeguard internal information. Microsoft Purview Information Barriers (IB) is supported in Microsoft Teams, SharePoint Online, and OneDrive for Business. A compliance administrator or IB administrator can define policies to allow or prevent communications between groups of users in Microsoft Teams.
C248: AI Data Exposure Controls (Real-Time)

Sheet Inventory
A1: Category | B1: Tool | C1: Current State | D1: MSFT Solutions Owned | E1: Additional MSFT Solutions | F1: Notes
A2: Identity | B2: SSO | E2: Entra / AAD (P2) Entra / AAD (P1) ID Governance Entra Suite
B3: MFA | E3: Entra / AAD (P2) Entra / AAD (P1)
B4: Identity Governance | E4: Entra / AAD (P2) Entra / AAD (P1) ID Governance Entra Suite
B5: B2B/B2C Identity | E5: Entra / AAD (P2) Entra / AAD (P1) ID Governance Entra Suite
B6: Adaptive RISK based Auth | E6: Entra / AAD (P2) Entra / AAD (P1)
B7: Privileged Access Management | E7: Priviliged Identity Management (Entra P2) Entra / AAD (P1) ID Governance Entra Suite
A8: Device | B8: Anti Virus | E8: Microsoft Defender (M365 E3 / Defender P1)
B9: Client EDR | E9: Microsoft Defender (M365 E3 / Defender P2)
B10: Server EDR | E10: Microsoft Defender for Cloud P2 (Azure Consumption) Cloud Workload Protection
B11: Cloud Posture Management | E11: Defender for Cloud Posture Management (Azure Consumption)
B12: Container Security | E12: Microsoft Defender for Cloud P2 (Azure Consumption) Cloud Workload Protection Defender for Cloud Posture Management (Azure Consumption)
B13: MAM | E13: EMS Microsoft Intune (M365 E3) Intune Premium
B14: MDM | E14: Microsoft Intune (M365 E3) Intune Premium
B15: Client Endpoint Update Management | E15: Microsoft Intune (M365 E3) Autopatch
B16: Server Update Management | E16: Automanage (Server) with Azure Arc Azure Update Management(Consumption)
B17: Adaptive Device Risk Conditional Access | E17: Microsoft Defender for Endpoint (P2/ M365 E5) Entra ID Conditional Access (M365 E3)
B18: App Allow/Deny Listing | E18: App Control for Business/Applocker (AKA Windows Defender Application Control (WDAC)) -Part of Windows and Intune
B19: Configuration Management | D19: Microsoft Intune (M365 E3) | E19: BICEP/ARM & Azure Azure Policy (Arc)
B20: Inventory | E20: Microsoft Graph. Azure Resource Graph Inventory - Azure Consumption. Intune + Intune Data Warehouse(M365 E3) Microsoft Exposure Management (M365 E3 & E5) Entra user, device, application inventory
A21: Security Ops | B21: SIEM | E21: Microsoft Sentinel
B22: ITSM / Ticket Management | F22: Strong Partnership with Partners like Servicenow
B23: AI Assisted Security | E23: Security Copilot (Azure Consumption - SCU - Security Compute Units
B24: MSSP - Inhouse or Partner | E24: Microsoft Defender Experts MISA - Microsoft Intelligence Security Association (Partners)
B25: Security Orchestration / Automation | E25: Defender XDR Automatic attack disruption (M365 E5) Defender Automated Investigation (M365 E5) Conditional Access Defender & Sentinel Runbooks Logic Apps (SOAR) Security Copilot
B26: CASB | E26: Microsoft Defender for Cloud Apps (M365 E5)
B27: Auditing | D27: Office 365 & Azure Audit Logs Advanced audting - 180 Days | E27: M365 E5 - Office 365 & Azure Audit Logs Advanced audting - 1 year and Feed into Sentinel
B28: Archiving | E28: M365 Archive - Consumption M365 Backup Connect Azure Subscription Billing
B29: Zero Day Attacks | E29: Microsoft Defender for Office 365 (M365 E5)- Includes safe links and attachments outlook, teams, sharepoint, onedrive, office
B30: Phishing | E30: Microsoft Defender for Office 365 (M365 E5) - Phishing campaign training and content
B31: 3rd Party Pen Testing | E31: MISA - Microsoft Intelligence Security Association (Partners)
B32: Threat Intelligence | E32: Microsoft Defender Threat Intelligence (Former RISK IQ) Included with Security Copilot
B33: Vulnerability Management / Exposure Management | E33: Defender Plan 1 (Intune Attack Surface Reduction) - M365 E3 Defender for Cloud Defender CSPM (Azure Consumption) Microsoft Defender Exposure Management (M365-E3/E5)- Many options | F33: Integration of data from these tools and other Microsoft Security tools like Microsoft Defender for Cloud, Microsoft Defender Cloud Security Posture Management and Microsoft Defender External Attack Surface Management is available with those licenses. Integration of non-Microsoft security tools will be a consumption-based cost based on number of assets in the connected security tool. The external connectors are free during public preview, and pricing will be announced before starting to bill for external connectors at GA.
B34: Compliance & Security Reporting | D34: Compliance Score, Secure Score | E34: Defender for Cloud Regulatory Compliance Templates -Included in MS Defender for Cloud P2 (Consumption). Compliance Manager Premium Templates (ADD-on) Premium Compliance Templates. | F34: Note Many options for templatized Security Reporting in Dashboards, Azure Workbooks (Insights), Azure Dashboards, and PowerBI
B35: File Integrity Management (FIM) | E35: Defender for Cloud - Windows Plan2 (Azure Consumption) Defender for Endpoing (M365 E5) | F35: “To provide File Integrity Monitoring (FIM), Microsoft Defender for Endpoint collects data from machines according to collection rules. When the current state of your system files is compared with the state during the previous scan, FIM notifies you about suspicious modifications,”
A36: Info Protection | B36: Content Encryption | E36: MSFT Information Protection Manual (P1/M365 E3) MSFT Information Protection - Automated (P2/M365 E3)
B37: DLP | E37: Office 365 DLP (M365-E3) Defender Endpoint DLP Teams DLP (M365-E5) | F37: DLP is just one of the Microsoft Purview tools that you'll use to help protect your sensitive items wherever they live or travel. You should understand the other tools in the Microsoft Purview tool set, how they interrelate, and work better together. See, Microsoft Purview tools to learn more about the information protection process.
B38: Endpoint DLP | E38: Purview Endpoint DLP
B39: Drive Encryption | E39: Bitlocker (M365-E3)
B40: eDiscovery | E40: Purview Ediscovery-Standard(M365 E3) Purview Ediscovery-Premium (M365 E5)
B41: Information Classification | E41: Purview Information Protection Manual Labels(P1/M365 E3) MSFT Information Protection - Automated (P2/M365 E3)
B42: Message Encryption | E42: Office 365 Message Encryption (P1/M365 E3)
B43: Data Governance | E43: MS Purview Data Governance (Meter consumption) - DGPU - Data Governance Processing Unit
B44: Data Protection & Backup | E44: Office 365 Message Encryption (P1/M365 E3)
A45: Network & Infra | B45: Network Detection and Response | E45: Defender Endpoint (P2 - M365 E5)
B46: Firewall | E46: Azure Firewall - Azure Consumption
B47: VPN / SASE solution | E47: Microsoft Entra Internet Access and Microsoft Entra Private Access. (Part of Entra Suite) Intune Premium (IOS/Android) Entra App Proxy (P1/M365 E3)
B48: Network Access Control | E48: Entra Private + Internet Access
A50: Biz Appp | B50: HR System of Record
B51: ERP
A53: Inventory | B53: Endpoint Summary
B54: Windows 11
B55: Windows 10
B56: Windows 7
B57: Server 2008
B58: Server 2012
B59: Server 2019
B60: Servers 2022
B61: Server 2025
B62: iOS
B63: Mac
B64: Android
B65: Linux (OS preference) - Redhat, etc..
... B74: AWS

Sheet MW Plan
A1: Task Name | B1: License | C1: Line Type | D1: Predecessors | E1: Priority | F1: Design and Planning | G1: Admin Configuration | H1: Deployment Time | I1: RAG: User Change (Impact) | J1: Comment | K1: Microsoft Resource Type | L1: Engagement Type | M1: Recommended use | N1: Key Stakeholder | O1: Risk Register / Audit Report Alignment | P1: Existing Third party Product | Q1: Contract End date | R1: Soft saving category | S1: Business Justification | T1: Resource Type | U1: Management Portal | V1: RBAC Role in Azure AD | W1: One Tenant, Multi Organization Scope | X1: Product Category | Y1: Zero Trust Pillar | Z1: Available with Unified Support (subject to contract) | AA1: Related Value Based Delivery (VBD) ? | AB1: Does the VBD belong to a Designated Engineering package (If so, which one) ? | AC1: Fasttrack Support Offering | AD1: SC Exam | AE1: ESI | AF1: MCAPS
A2: Productivity | B2: __ | C2: __ | D2: __ | E2: __ | F2: __ | G2: __ | H2: __ | I2: __ | J2: __ | K2: __ | L2: __ | M2: __ | N2: __ | O2: __ | P2: __ | Q2: __ | R2: __ | S2: __ | T2: __ | U2: __ | V2: __ | W2: __ | X2: __ | Y2: __ | Z2: __ | AA2: __ | AB2: __ | AC2: __
A3: Collaboration | B3: _ | C3: _ | D3: _ | E3: _ | F3: _ | G3: _ | H3: _ | I3: _ | J3: _ | K3: _ | L3: _ | M3: _ | N3: _ | O3: _ | P3: _ | Q3: _ | R3: _ | S3: _ | T3: _ | U3: _ | V3: _ | W3: _ | X3: _ | Y3: _ | Z3: _ | AA3: _ | AB3: _ | AC3: _
A4: Microsoft Apps for Enterprise (Office ProPlus) | B4: M365 E3 | C4: Product | E4: - | J4: - | K4: - | L4: - | Q4: Productivity | R4: Always latest and greatest version of Office deployed using the modern Click to Run method. | S4: End user compute | T4: https://endpoint.microsoft.com | U4: N/A (On-prem activity) | V4: Organisation Specific (on-premises deployment) | W4: Productivity Suite | X4: Applications | Y4: Yes | AB4: Microsoft 365 Apps; App Assure; Microsoft Teams
A5: SharePoint Online | B5: M365 E3, M365 F3 | C5: Product | E5: - | F5: _ | G5: _ | H5: _ | I5: _ | K5: - | L5: - | M5: - | N5: _ | O5: _ | P5: _ | Q5: _ | R5: _ | S5: _ | T5: _ | U5: _ | V5: _ | W5: _ | X5: _ | Y5: _ | Z5: _ | AA5: WorkshopPLUS - Microsoft Azure: Identity | AB5: Zero Trust: Identity
A6: OneDrive for Business | B6: M365 E3, M365 F3 | C6: Product | E6: - | K6: - | L6: - | M6: - | R6: Risk Reduction | S6: Reduces expose of potential PII data and gives control to admins who can grant consent if needed | T6: Identity | U6: https://entra.microsoft.com | V6: Global Admin | W6: Tenant Wide | X6: Identity and Access Management | Y6: Applications | Z6: Yes | AB6: Zero Trust: Identity
A7: Exchange Online | B7: M365 E3, M365 F3 | C7: Product | E7: - | K7: - | L7: - | M7: - | R7: Risk Reduction | S7: Stops users from using common passwords and forces them (politely) to set not a only a complex password but one that is more unique and less guessable. In turn this, coupled with MFA, removes the need for users to changes their passwords on a regular basis. This can help reduce load on the helpdesk for forgotten passwords or users physically writing down passwords and taping to desks | T7: Identity, Server Infrastructure | U7: https://entra.microsoft.com | V7: Security Administrator | W7: Tenant Wide | X7: Identity and Access Management | Y7: Identity | Z7: Yes | AB7: Zero Trust: Identity | AC7: Azure AD: Secure Foundation infrastructure
A8: Planner | B8: M365 E3, M365 F3 | C8: Feature | E8: - | K8: - | L8: - | M8: - | R8: Risk Reduction | S8: Allows Organizations to define the conditional access conditions a user must go through to enrol into MFA or Self Service Password Reset (SSPR). This helps validate the user is a member of the Organization and not an attacker with phished credentials creating trust through MFA | T8: Identity | U8: https://entra.microsoft.com | V8: Conditional Access Administrator | W8: Scoped (to CA policy) | X8: Identity and Access Management | Y8: Identity | Z8: Yes | AB8: Zero Trust: Identity | AC8: Azure AD: Secure Foundation infrastructure
A9: Microsoft Whiteboard | B9: M365 E3, M365 F3 | C9: Product | E9: - | K9: - | L9: - | M9: - | R9: Risk Reduction | S9: Stops 99.9% of Identity based attacks. As identity is the control plane, MFA is essential protection. Factors of authentication are broken down into something you know (password/PIN), something you have (i.e. phone or token) and something you are (biometrics). The latter two typically can only exist in one place at a time giving trust that the user who provides these is who they claim to be. | T9: Identity, Helpdesk, End User Compute | U9: https://entra.microsoft.com | V9: Authentication Administrator | W9: Organization Specific (Administrative Units) | X9: Identity and Access Management | Y9: Identity | Z9: Yes | AB9: Zero Trust: Identity | AC9: Azure AD: Secure Foundation infrastructure
A10: Stream | C10: Product | E10: - | K10: - | L10: - | M10: - | R10: Operational, Risk Reduction, Productivity | S10: Can significantly reduce load on the help desk by allowing users to reset their own passwords. Provides greater levels of validation that the user is who they claim to be through MFA when resetting passwords. Also allows a user to reset their password anytime, even outside of helpdesk operating hours. Can also be used as a response action, in line with Azure Identity Protection, to help remediate compromised accounts | T10: Identity, Helpdesk, End User Compute | U10: https://entra.microsoft.com | V10: User Administrator + Global Administrator | W10: Tenant wide settings, scoped deployment | X10: Identity and Access Management | Y10: Identity | Z10: Yes | AB10: Zero Trust: Identity | AC10: Azure AD: Secure Foundation infrastructure; Azure AD: Automation & Efficiencies
A11: Microsoft Syntex | C11: Product | E11: - | K11: - | L11: - | M11: - | R11: Risk Reduction, Operational | S11: The cornerstone of modern authentication providing adaptive access controls based on users, devices, applications, data and risk. Effectively ensuring that right users have the right level of access based on the levels of controls they can adhere to. i.e., users on a fully managed device and MFA can access rich clients and download data whilst users on unmanaged (BYOPC) devices can be restricted to the browser and session controls can extraction of data) | T11: Identity, Security | U11: https://entra.microsoft.com | V11: Conditional Access Administrator | W11: Scoped (to CA policy) | X11: Identity and Access Management | Y11: Identity | Z11: Yes | AB11: Zero Trust: Identity | AC11: Azure AD: Secure Foundation infrastructure
A12: Mobile Apps | C12: Feature | E12: - | K12: - | L12: - | M12: - | R12: Risk Reduction, Operational | S12: Authentication strength can be set in the grant controls of a conditional access policy. This allows your Organization to use stronger authentication methods for more sensitive applications. When used with Authentication Context, your Organization can require more strict identity verification for access to specific data.
A13: Delve | C13: Feature | E13: - | K13: - | L13: - | M13: - | R13: Operational, Risk Reduction, Productivity | S13: Authentication Context allows you set strict or heavily defined security controls over specific applications and data. For example, users, including guests, can be accessing data in a SharePoint site, but some data might be more sensitive. When applying a label with protection (RMS encryption), this block access to the data in Line of Business applications or break processes. With Authentication context, the access to the data can restricted in Conditional Access. For example, when accessing the specific data within the SharePoint site, the Conditional Access policy may require a compliant device or a stronger Authentication Strength to access. In turn, this can reduce the number of conditional access policies required to great the equivalent level of granular access. | U13: https://entra.microsoft.com and https://compliance.microsoft.com
A14: Microsoft Forms | C14: Product | E14: - | K14: - | L14: - | M14: - | R14: Operational, Risk Reduction, Productivity | S14: Authentication Context allows you set strict or heavily defined security controls over specific applications and data. For example, users, including guests, can be accessing data in a SharePoint site, but some data might be more sensitive. When applying a label with protection (RMS encryption), this block access to the data in Line of Business applications or break processes. With Authentication context, the access to the data can restricted in Conditional Access. For example, when accessing the specific data within the SharePoint site, the Conditional Access policy may require a compliant device or a stronger Authentication Strength to access. In turn, this can reduce the number of conditional access policies required to great the equivalent level of granular access. | U14: https://entra.microsoft.com and https://compliance.microsoft.com
A15: To Do | C15: Product | E15: - | K15: - | L15: - | M15: - | R15: Operational, Risk Reduction, Productivity | S15: Authentication Context allows you set strict or heavily defined security controls over specific applications and data. For example, users, including guests, can be accessing data in a SharePoint site, but some data might be more sensitive. When applying a label with protection (RMS encryption), this block access to the data in Line of Business applications or break processes. With Authentication context, the access to the data can restricted in Conditional Access. For example, when accessing the specific data within the SharePoint site, the Conditional Access policy may require a compliant device or a stronger Authentication Strength to access. In turn, this can reduce the number of conditional access policies required to great the equivalent level of granular access. | U15: https://entra.microsoft.com and https://compliance.microsoft.com
A16: ClipChamp | C16: Product | E16: - | K16: - | L16: - | M16: - | R16: Operational, Risk Reduction, Productivity | S16: Authentication Context allows you set strict or heavily defined security controls over specific applications and data. For example, users, including guests, can be accessing data in a SharePoint site, but some data might be more sensitive. When applying a label with protection (RMS encryption), this block access to the data in Line of Business applications or break processes. With Authentication context, the access to the data can restricted in Conditional Access. For example, when accessing the specific data within the SharePoint site, the Conditional Access policy may require a compliant device or a stronger Authentication Strength to access. In turn, this can reduce the number of conditional access policies required to great the equivalent level of granular access. | U16: https://entra.microsoft.com and https://compliance.microsoft.com
A17: Microsoft Lists | C17: Feature | E17: - | K17: - | L17: - | M17: - | R17: Operational, Risk Reduction, Productivity | S17: Authentication Context allows you set strict or heavily defined security controls over specific applications and data. For example, users, including guests, can be accessing data in a SharePoint site, but some data might be more sensitive. When applying a label with protection (RMS encryption), this block access to the data in Line of Business applications or break processes. With Authentication context, the access to the data can restricted in Conditional Access. For example, when accessing the specific data within the SharePoint site, the Conditional Access policy may require a compliant device or a stronger Authentication Strength to access. In turn, this can reduce the number of conditional access policies required to great the equivalent level of granular access. | U17: https://entra.microsoft.com and https://compliance.microsoft.com
A18: Microsoft Sway | C18: Feature | E18: - | K18: - | L18: - | M18: - | R18: Operational, Risk Reduction, Productivity | S18: Authentication Context allows you set strict or heavily defined security controls over specific applications and data. For example, users, including guests, can be accessing data in a SharePoint site, but some data might be more sensitive. When applying a label with protection (RMS encryption), this block access to the data in Line of Business applications or break processes. With Authentication context, the access to the data can restricted in Conditional Access. For example, when accessing the specific data within the SharePoint site, the Conditional Access policy may require a compliant device or a stronger Authentication Strength to access. In turn, this can reduce the number of conditional access policies required to great the equivalent level of granular access. | U18: https://entra.microsoft.com and https://compliance.microsoft.com
A19: Reporting and Insights
A20: Power BI | C20: Product | E20: - | F20: _ | G20: _ | H20: _ | I20: _ | K20: - | L20: - | M20: - | N20: _ | O20: _ | P20: _ | Q20: _ | R20: _ | S20: _ | T20: _ | U20: _ | V20: _ | W20: _ | X20: _ | Y20: _ | Z20: _
A21: Power Automate | C21: Product | E21: - | K21: - | L21: - | M21: - | R21: Operational, Productivity | S21: Significantly reduce or remove on-premises Exchange servers and all it's associated requirements leaving uses with an always up to date Exchange, access from anywhere, significantly larger mailboxes, transport rules and advanced compliance features on top of other benefits | T21: Active Directory, Exchange, Server infrastructure | U21: https://admin.microsoft.com | V21: Organization Management | W21: Scoped (domain, OU, Group filtering) | X21: Email | Y21: Applications | Z21: Yes
A22: Power Apps & Agents | C22: Product | E22: - | K22: - | L22: - | M22: - | R22: Operational, Productivity | S22: Migrate from legacy file shares to modern document management with SharePoint Online, providing an EDRM system, structured data, better searching, larger storage capacity, better insights, secure access from anywhere and access to advanced compliance features on top of other benefits | T22: Information Governance, Storage, Solutions Architect | U22: https://admin.microsoft.com | V22: SharePoint Admin | W22: Scoped (domain, OU, Group filtering) | X22: Document Management/Internet/EDRMS | Y22: Applications/Data | Z22: Yes | AA22: Activate SharePoint Online Migration MIP | AC22: SPO/ ODfB; Data Migration
A23: Microsoft Teams | E23: -
A24: Teams Phone | C24: Product | E24: - | K24: - | L24: - | M24: - | R24: Operational, Productivity | S24: Migrate from legacy home drives to modern document management with OneDrive for Business, providing an EDRM system, structured data, better searching, unlimited storage capacity, secure access from anywhere and access to advanced compliance features on top of other benefits | T24: Information Governance, Storage, Solutions Architect | U24: https://admin.microsoft.com | V24: SharePoint Admin | W24: Scoped (domain, OU, Group filtering) | X24: Document Management/Internet/EDRMS | Y24: Applications/Data | Z24: Yes | AC24: SPO/ ODfB; Data Migration
A25: Virtual Appointments | C25: Feature | E25: - | K25: - | L25: - | M25: - | R25: Operational, Risk Reduction | S25: Conditional Access is your frontline for access into your environment, having professional services review and refine your policies can improve your security posture, ensure you are taking a modern approach and potentially improve the end user experience. | T25: External | U25: N/A | V25: N/A | X25: Professional Services | Z25: Yes | AB25: Zero Trust: Identity
A26: Activity Reports | C26: Feature | E26: - | K26: - | L26: - | M26: -
A27: Meeting Protection | C27: Feature | E27: - | K27: - | L27: - | M27: -
A28: Calling Plan | C28: Product | E28: - | K28: - | L28: - | M28: -
A29: Teams Rooms | C29: Product | E29: - | K29: - | L29: - | M29: - | R29: Operational | S29: Allows users to use the same additional factors of authentication they use with Azure MFA for on-premises services, such as VPNs and RDP access. Reduces the need to have yet more MFA tokens or other MFA services. | T29: Server infrastructure, Identity, Helpdesk, End User Compute | U29: On-premises configuration | V29: Authentication Policy Administrator | W29: Organization Specific (on-premises deployment) | X29: Identity and Access Management | Y29: Identity/Applications | Z29: Yes | AB29: Zero Trust: Identity
A30: Teams Channels | C30: Feature | E30: - | K30: - | L30: - | M30: - | R30: Risk Reduction, Operational | S30: Add risks as a condition to conditional access. Not only can this help work towards your Zero Trust strategy. For example, if risk is set to low with a requirement for MFA for all users, they will get additional MFA prompts. As they build a pattern of behaviour within the service (only seen by the A.I. / ML engines), and conform to this pattern they will be challenged for MFA less and less. This can help improve the user experience (less MFA prompts) whilst maintaining a high level of security. | T30: Identity, Security | U30: https://entra.microsoft.com | V30: Security Administrator | W30: Scoped (to CA policy) | X30: Identity and Access Management | Y30: Identity | Z30: Yes | AB30: Zero Trust: Identity | AC30: Azure AD: Secure Foundation Infrastructure
A31: Teams 3rd Party Apps | C31: Feature | E31: - | K31: - | L31: - | M31: - | R31: Risk Reduction, Operational | S31: Brings more control for BYOD (especially BOYPC) and external users. Limits sessions on unmanaged devices to browser, controlling/blocking the transfer of data in and out of your environment | T31: Identity, Security, End User Compute | U31: https://security.microsoft.com | V31: Security Administrator | W31: Scoped (to CA policy) | X31: Identity and Access Management | Y31: Identity | Z31: Yes | AB31: Zero Trust: Identity
A32: Teams Audio Conferencing | C32: Product | E32: - | K32: - | L32: - | M32: - | R32: Risk Reduction | S32: Continuously re-evaluates access, enforcing conditional access controls when there is a change (such as a user moving from a trusted location to an untrusted one) rather than relying on session timeouts. Greatly improves security without impacting user experience | U32: https://entra.microsoft.com | W32: Scoped (users and groups) | X32: Identity and Access Management | Y32: Identity | Z32: Yes
A33: Teams Phone Standard | C33: Product | E33: - | K33: - | L33: - | M33: - | R33: Risk Reduction | S33: Provide the conditions under which a user can register a device into Azure AD, such as being in a trusted location or requiring MFA - this helps ensure that is a user of your Organization enrolling a device and not an attacker trying to gain device trust. | T33: Identity, End User Compute | U33: https://entra.microsoft.com | V33: Authentication Policy Administrator | W33: Tenant Wide | X33: Identity and Access Management/Device Management | Y33: Identity/Devices | Z33: Yes | AA33: Zero Trust Foundations Assessment | AB33: Zero Trust: Identity | AC33: Intune MAM/MDM/Cloud Attach; Windows 10
A34: Teams Phone Premium | C34: Product | E34: -
A35: Teams Meeting Reporting | C35: Feature | E35: -
A36: Dataverse for Teams | C36: Product | E36: -
A37: Microsoft Teams Shifts | C37: Feature | E37: -
A38: Microsoft Teams Recording | C38: Feature | E38: -
A39: Microsoft Teams Town Hall | C39: Feature | E39: -
A40: Microsoft Teams - baseline | C40: Product | E40: -
A41: Employee Productivity
A42: Viva Topics | B42: Viva Suite, Viva Topics | C42: Product | E42: - | K42: - | L42: - | M42: - | R42: Operational | S42: Allows for synchronization of on-premises Active Directory accounts into Azure AD | T42: Identity | U42: On-premises (ID Fix, dsa.msc) | V42: N/A (On-prem activity) | W42: Organization Specific (on-premises deployment) | X42: Identity and Access Management | Y42: Identity | Z42: Yes | AC42: Core onboarding: Identity Integration; Azure AD: Secure Foundation Infrastructure
A43: Viva Insights
A44: Viva Insights Personal | B44: M365 E3, M365 F3 | C44: Product | E44: - | K44: - | L44: - | M44: - | R44: Operational | S44: Creates a relationship between on-premises AD Accounts and AD accounts to make them appear as one account (single identity, effectively a hybrid identity) | T44: Identity, Server Infrastructure | U44: https://portal.azure.com for cloud provisioning | V44: Global Admin | W44: Scoped (domain, OU, Group filtering) | X44: Identity and Access Management | Y44: Identity | Z44: Yes | AA44: Onboarding Accelerator – Azure Active Directory: Features Deployment (Base) | AB44: Zero Trust: Identity | AC44: Core onboarding: Identity Integration; Azure AD: Secure Foundation Infrastructure
A45: Viva Premium Personal Insights and Experiences | B45: M365 E5
A46: Viva Insights Manager and Leader Insights and Experiences | B46: Viva Suite, Viva Insights, Viva Workplace Analytics and Employee Feedback
A47: Viva Learning | B47: M365 E3, M365 F3 | C47: Product | E47: - | K47: - | L47: - | M47: - | R47: Productivity | S47: Allows for seamless single sign on whilst also removing the need for AD FS servers. This also means no reliance on any servers for authentication on-premises reducing surface area of attack | T47: Identity, Server Infrastructure | U47: On-premises configuration | V47: Global Admin | W47: Organization Specific (Domain Specific) | X47: Identity and Access Management | Y47: Identity | Z47: Yes | AA47: Zero Trust Foundations Assessment | AB47: Zero Trust: Identity
A48: Viva Connections | C48: Product | E48: - | K48: - | L48: - | M48: - | R48: Productivity | S48: Always latest and greatest version of Office deployed using the modern Click to Run method. | T48: End user compute | U48: https://endpoint.microsoft.com | V48: N/A (On-prem activity) | W48: Organization Specific (on-premises deployment) | X48: Productivity Suite | Y48: Applications | Z48: Yes | AC48: Microsoft 365 Apps; App Assure; Microsoft Teams
A49: Viva Goals | C49: Product | E49: -
A50: Viva Engage
A51: Viva Engage | B51: M365 E3, M365 F3 | C51: Product | E51: - | K51: - | L51: - | M51: - | R51: Risk Reduction | S51: This has less of a use case in Zero Trust, but can still be used to help validate users when setting up MFA or enrolling devices. I.e., they must pass through physical security before setting up digital security | T51: Identity, Networking | U51: https://entra.microsoft.com | V51: Conditional Access Administrator | W51: Scoped (named locations) | X51: Identity and Access Management | Y51: Identity | Z51: Yes | AB51: Zero Trust: Identity | AC51: Azure AD: Secure Foundation infrastructure
A52: Viva Engage Advanced Security | B52: M365 E5 Compliance
A53: Viva Engage Leadership Corner | B53: Viva Suite, Viva C&C | C53: Feature
A54: Viva Engage AMA (Ask Me Anything) | B54: Viva Suite, Viva C&C
A55: Viva Engage Advanced Analytics | B55: Viva Suite, Viva C&C
A56: Viva Engage Storyline Delegate Posting | B56: Viva Suite, Viva C&C
A57: Viva Glint | C57: Product | E57: -
A58: Viva Pulse
A59: Viva Amplify
A60: Microsoft 365 Add-on Solutions
A61: Microsoft Visio
A62: Visio Plan 1 | C62: Product | E62: - | K62: - | L62: - | M62: - | R62: Operational, Risk Reduction, Productivity | S62: Authentication Context allows you set strict or heavily defined security controls over specific applications and data. For example, users, including guests, can be accessing data in a SharePoint site, but some data might be more sensitive. When applying a label with protection (RMS encryption), this block access to the data in Line of Business applications or break processes. With Authentication context, the access to the data can restricted in Conditional Access. For example, when accessing the specific data within the SharePoint site, the Conditional Access policy may require a compliant device or a stronger Authentication Strength to access. In turn, this can reduce the number of conditional access policies required to great the equivalent level of granular access. | U62: https://entra.microsoft.com and https://compliance.microsoft.com
A63: Visio Plan 2 | C63: Product | E63: - | K63: - | L63: - | M63: - | R63: Operational, Risk Reduction, Productivity | S63: Authentication Context allows you set strict or heavily defined security controls over specific applications and data. For example, users, including guests, can be accessing data in a SharePoint site, but some data might be more sensitive. When applying a label with protection (RMS encryption), this block access to the data in Line of Business applications or break processes. With Authentication context, the access to the data can restricted in Conditional Access. For example, when accessing the specific data within the SharePoint site, the Conditional Access policy may require a compliant device or a stronger Authentication Strength to access. In turn, this can reduce the number of conditional access policies required to great the equivalent level of granular access. | U63: https://entra.microsoft.com and https://compliance.microsoft.com
A64: Project Management - Microsoft Project
A65: Project Plan 1 | C65: Product | E65: - | K65: - | L65: - | M65: - | R65: Operational, Risk Reduction, Productivity | S65: Authentication Context allows you set strict or heavily defined security controls over specific applications and data. For example, users, including guests, can be accessing data in a SharePoint site, but some data might be more sensitive. When applying a label with protection (RMS encryption), this block access to the data in Line of Business applications or break processes. With Authentication context, the access to the data can restricted in Conditional Access. For example, when accessing the specific data within the SharePoint site, the Conditional Access policy may require a compliant device or a stronger Authentication Strength to access. In turn, this can reduce the number of conditional access policies required to great the equivalent level of granular access. | U65: https://entra.microsoft.com and https://compliance.microsoft.com
A66: Project Plan 3 | C66: Product | E66: - | K66: - | L66: - | M66: - | R66: Operational, Risk Reduction, Productivity | S66: Authentication Context allows you set strict or heavily defined security controls over specific applications and data. For example, users, including guests, can be accessing data in a SharePoint site, but some data might be more sensitive. When applying a label with protection (RMS encryption), this block access to the data in Line of Business applications or break processes. With Authentication context, the access to the data can restricted in Conditional Access. For example, when accessing the specific data within the SharePoint site, the Conditional Access policy may require a compliant device or a stronger Authentication Strength to access. In turn, this can reduce the number of conditional access policies required to great the equivalent level of granular access. | U66: https://entra.microsoft.com and https://compliance.microsoft.com
A67: Project Plan 5 | C67: Product | E67: - | K67: - | L67: - | M67: - | R67: Operational, Risk Reduction, Productivity | S67: Authentication Context allows you set strict or heavily defined security controls over specific applications and data. For example, users, including guests, can be accessing data in a SharePoint site, but some data might be more sensitive. When applying a label with protection (RMS encryption), this block access to the data in Line of Business applications or break processes. With Authentication context, the access to the data can restricted in Conditional Access. For example, when accessing the specific data within the SharePoint site, the Conditional Access policy may require a compliant device or a stronger Authentication Strength to access. In turn, this can reduce the number of conditional access policies required to great the equivalent level of granular access. | U67: https://entra.microsoft.com and https://compliance.microsoft.com
A68: Microsoft Surface Hardware
A69: Surface Hub | C69: Device | E69: - | F69: _ | G69: _ | H69: _ | I69: _ | K69: - | L69: - | M69: - | N69: _ | O69: _ | P69: _ | Q69: _ | R69: _ | S69: _ | T69: _ | U69: _ | V69: _ | W69: _ | X69: _ | Y69: _ | Z69: _ | AA69: Activate Azure with Multi-Factor Authentication and Conditional Access | AB69: Zero Trust: Identity
A70: Surface Devices | C70: Device | E70: - | K70: - | L70: - | M70: - | R70: Risk Reduction | S70: Reduces surface area of attacks and stops the use of weak authentication methods that does not support MFA (strong authentication). Allowing legacy authentication in any capacity should be highlight on your risk register | T70: Identity, Security | U70: https://entra.microsoft.com | V70: Conditional Access Administrator | W70: Scoped (to CA policy) | X70: Identity and Access Management | Y70: Identity/Applications | Z70: Yes | AB70: Zero Trust: Identity

Sheet Accessibility
A1: Caveat
B2: Requirements | C2: Where it can support | D2: Description | E2: Use case suggestions
A3: Comon configuration
A4: Windows Settings
A6: Vision
A7: Windows Features
A8: Read Aloud
A9: Colour filters
A12: Microsoft 365
A13: Office on the web
A16: Apps for Enterprise
A18: Teams
A20: Hearing
A21: Windows Features
... A25: Interaction

Sheet Data Validations
A1: Engagement Type | B1: Recommended Use | C1: Priority | E1: Choose Language
A2: - | B2: - | C2: - | D2: Product | E2: EN-GB
A3: Assessment | B3: Current Contract | C3: D | D3: Feature | E3: EN-US
A4: Implementation | B4: Next Contract | C4: W | D4: Configuration
A5: Training (BAU) | B5: Optional (Suggestion) | C5: 1 | D5: Consideration
C6: 2 | D6: Process
C7: 3 | D7: Suggestion
C8: 4
